{
  "updated_at": "2026-05-08T01:35:11.098406+00:00",
  "deals": [
    {
      "asin": "B0GXZF4C7N",
      "title": "Mini Washing Machine for Clothes",
      "price": "₹1,699",
      "price_num": 1699,
      "original_price": "₹3,999",
      "discount_pct": 57,
      "effective_price": "₹1,649",
      "image_url": "https://m.media-amazon.com/images/I/51jBBS2TWGL._SL1500_.jpg",
      "category": "⚡ Electronics",
      "source": "amazon",
      "is_lowest_ever": false,
      "lowest_ever": "₹1,499",
      "average_price": "₹1,682",
      "highest_price": "₹1,699",
      "vs_avg_str": "1% above avg (avg ₹1,682)",
      "vs_avg_pct": -1,
      "best_card_label": "₹50 off via Amazon Pay",
      "best_card_discount": 50,
      "coupon": null,
      "coupon_num": 0,
      "emi_savings": null,
      "score": 20,
      "rating": 5.0,
      "affiliate_link": "https://www.amazon.in/dp/B0GXZF4C7N?tag=techeasy0d1-21&linkCode=ll1&linkId=B0GXZF4C7N&ref_=as_li_ss_tl",
      "posted_at": "2026-05-08T01:32:46.120657+00:00"
    },
    {
      "asin": "B0DXQ5V717",
      "title": "Ionstar 7 Kg Semi Automatic Washing Machine Top Load",
      "price": "₹7,290",
      "price_num": 7290,
      "original_price": "₹19,999",
      "discount_pct": 63,
      "effective_price": "₹6,790",
      "image_url": "https://m.media-amazon.com/images/I/619DloW+FgL._SL1080_.jpg",
      "category": "⚡ Electronics",
      "source": "amazon",
      "is_lowest_ever": false,
      "lowest_ever": "₹6,690",
      "average_price": "₹7,216",
      "highest_price": "₹9,503",
      "vs_avg_str": "1% above avg (avg ₹7,216)",
      "vs_avg_pct": -1,
      "best_card_label": "₹500 off via Bank",
      "best_card_discount": 500,
      "coupon": null,
      "coupon_num": 0,
      "emi_savings": "₹236 EMI interest savings",
      "score": 20,
      "rating": 4.4,
      "affiliate_link": "https://www.amazon.in/dp/B0DXQ5V717?tag=techeasy0d1-21&linkCode=ll1&linkId=B0DXQ5V717&ref_=as_li_ss_tl",
      "posted_at": "2026-05-08T01:32:39.205674+00:00"
    },
    {
      "asin": "B0DXQ575B9",
      "title": "Ionstar 7 Kg 5 Star Semi Automatic Top Loading Washing Machine 2025 Jet Pulsator/Magic Filter/Air Dryer/1500 RPM Motor/Rat Mesh/Buzzer/Wheels,1 Year Comprehensive Free Extended Warranty(STAR70-AQUA-M)",
      "price": "₹7,290",
      "price_num": 7290,
      "original_price": "₹59,990",
      "discount_pct": 87,
      "effective_price": null,
      "image_url": "",
      "category": "⚡ Electronics",
      "source": "amazon",
      "is_lowest_ever": false,
      "lowest_ever": "₹6,690",
      "average_price": "₹7,293",
      "highest_price": "₹9,127",
      "vs_avg_str": "0% above avg (avg ₹7,293)",
      "vs_avg_pct": 0,
      "best_card_label": null,
      "best_card_discount": 0,
      "coupon": null,
      "coupon_num": 0,
      "emi_savings": null,
      "score": 20,
      "rating": 4.6,
      "affiliate_link": "https://www.amazon.in/dp/B0DXQ575B9?tag=techeasy0d1-21&linkCode=ll1&linkId=B0DXQ575B9&ref_=as_li_ss_tl",
      "posted_at": "2026-05-08T01:32:32.366695+00:00"
    },
    {
      "asin": "B0DXQ5MQCF",
      "title": "Ionstar 7.5 Kg Semi Automatic Washing Machine - 5 Star Rated - 2025 - Top Load - Jet Pulsator - Magic Filter - Special Air Dryer - Buzzer - Wheels - Powerful Copper Motor - 1500 RPM (STAR75-AQUA-G)",
      "price": "₹7,475",
      "price_num": 7475,
      "original_price": "₹19,999",
      "discount_pct": 62,
      "effective_price": "₹6,975",
      "image_url": "https://m.media-amazon.com/images/I/61AUG4hDW-L._SL1080_.jpg",
      "category": "⚡ Electronics",
      "source": "amazon",
      "is_lowest_ever": false,
      "lowest_ever": "₹6,750",
      "average_price": "₹7,211",
      "highest_price": "₹9,367",
      "vs_avg_str": "3% above avg (avg ₹7,211)",
      "vs_avg_pct": -3,
      "best_card_label": "₹500 off via Bank",
      "best_card_discount": 500,
      "coupon": null,
      "coupon_num": 0,
      "emi_savings": "₹242 EMI interest savings",
      "score": 20,
      "rating": 4.3,
      "affiliate_link": "https://www.amazon.in/dp/B0DXQ5MQCF?tag=techeasy0d1-21&linkCode=ll1&linkId=B0DXQ5MQCF&ref_=as_li_ss_tl",
      "posted_at": "2026-05-08T01:32:27.195658+00:00"
    },
    {
      "asin": "B0CW62435R",
      "title": "Aquaguard Sure Delight RO+MC 1X Water Purifier",
      "price": "₹7,807",
      "price_num": 7807,
      "original_price": "₹24,999",
      "discount_pct": 68,
      "effective_price": "₹6,807",
      "image_url": "https://m.media-amazon.com/images/I/41gt305ECFL._SL1100_.jpg",
      "category": "🔥 Hot Deal",
      "source": "desidime",
      "is_lowest_ever": false,
      "lowest_ever": "₹5,999",
      "average_price": "₹6,990",
      "highest_price": "₹13,000",
      "vs_avg_str": "11% above avg (avg ₹6,990)",
      "vs_avg_pct": -11,
      "best_card_label": "₹1,000 off via select Credit",
      "best_card_discount": 1000,
      "coupon": null,
      "coupon_num": 0,
      "emi_savings": "₹253 EMI interest savings",
      "score": 21,
      "rating": 4.2,
      "affiliate_link": "https://www.amazon.in/dp/B0CW62435R?tag=techeasy0d1-21&linkCode=ll1&linkId=B0CW62435R&ref_=as_li_ss_tl",
      "posted_at": "2026-05-08T01:32:20.220397+00:00"
    },
    {
      "asin": "B081Q8WKCB",
      "title": "Ant Esports KM540 Gaming Keyboard and Mouse Combo",
      "price": "₹999",
      "price_num": 999,
      "original_price": "₹10,215",
      "discount_pct": 90,
      "effective_price": null,
      "image_url": "https://m.media-amazon.com/images/I/718wvGJlouL._SL1500_.jpg",
      "category": "🎮 Video Games",
      "source": "amazon",
      "is_lowest_ever": false,
      "lowest_ever": "₹949",
      "average_price": "₹1,592",
      "highest_price": "₹2,650",
      "vs_avg_str": "37% below avg (avg ₹1,592)",
      "vs_avg_pct": 37,
      "best_card_label": "₹29 off via Amazon Pay",
      "best_card_discount": 29,
      "coupon": null,
      "coupon_num": 0,
      "emi_savings": null,
      "score": 50,
      "rating": 4.1,
      "affiliate_link": "https://www.amazon.in/dp/B081Q8WKCB?tag=techeasy0d1-21&linkCode=ll1&linkId=B081Q8WKCB&ref_=as_li_ss_tl",
      "posted_at": "2026-05-08T01:32:14.275763+00:00"
    },
    {
      "asin": "B0GYJLSV3P",
      "title": "Portable Washing Machine, 16L Mini Washing Machine With Spin Basket, Small Portable Washer Machine Suitable for Underwear Small Clothes Dryer Deep Cleaning A1",
      "price": "₹1,499",
      "price_num": 1499,
      "original_price": "₹1,84,900",
      "discount_pct": 99,
      "effective_price": null,
      "image_url": "https://m.media-amazon.com/images/I/51jBBS2TWGL._SL1500_.jpg",
      "category": "⚡ Electronics",
      "source": "amazon",
      "is_lowest_ever": true,
      "lowest_ever": "₹1,499",
      "average_price": "₹1,499",
      "highest_price": "₹1,499",
      "vs_avg_str": "0% above avg (avg ₹1,499)",
      "vs_avg_pct": 0,
      "best_card_label": "₹44 off via Amazon Pay",
      "best_card_discount": 44,
      "coupon": null,
      "coupon_num": 0,
      "emi_savings": null,
      "score": 60,
      "rating": 4.3,
      "affiliate_link": "https://www.amazon.in/dp/B0GYJLSV3P?tag=techeasy0d1-21&linkCode=ll1&linkId=B0GYJLSV3P&ref_=as_li_ss_tl",
      "posted_at": "2026-05-08T01:32:08.201305+00:00"
    },
    {
      "asin": "B0DDTVPH7V",
      "title": "Voltas Beko, A Tata Product 10 Kg 5 Star Fully-Automatic Top Loading Washing Machine (WTL1006UEA/OBS1060, Grey, Double Waterfall Technology)",
      "price": "₹18,990",
      "price_num": 18990,
      "original_price": "₹47,990",
      "discount_pct": 60,
      "effective_price": "₹17,240",
      "image_url": "https://m.media-amazon.com/images/I/711h6-YUwVL._SL1500_.jpg",
      "category": "⚡ Electronics",
      "source": "amazon",
      "is_lowest_ever": true,
      "lowest_ever": "₹18,990",
      "average_price": "₹19,279",
      "highest_price": "₹22,990",
      "vs_avg_str": "1% below avg (avg ₹19,279)",
      "vs_avg_pct": 1,
      "best_card_label": "₹1,750 off via select Credit",
      "best_card_discount": 1750,
      "coupon": null,
      "coupon_num": 0,
      "emi_savings": "₹1,490 EMI interest savings",
      "score": 62,
      "rating": 4.3,
      "affiliate_link": "https://www.amazon.in/dp/B0DDTVPH7V?tag=techeasy0d1-21&linkCode=ll1&linkId=B0DDTVPH7V&ref_=as_li_ss_tl",
      "posted_at": "2026-05-08T01:32:01.341015+00:00"
    },
    {
      "asin": "B0CGPVF1LQ",
      "title": "Buy DDLC 3MP 4G SIM Outdoor CCTV WiFi Bullet Wireless Security",
      "price": "₹2,499",
      "price_num": 2499,
      "original_price": "₹4,999",
      "discount_pct": 50,
      "effective_price": "₹2,376",
      "image_url": "https://m.media-amazon.com/images/I/51S-2rOCUBL._SL1031_.jpg",
      "category": "⚡ Electronics",
      "source": "amazon",
      "is_lowest_ever": false,
      "lowest_ever": "₹2,199",
      "average_price": "₹2,454",
      "highest_price": "₹2,799",
      "vs_avg_str": "1% above avg (avg ₹2,454)",
      "vs_avg_pct": -1,
      "best_card_label": "₹74 off via Amazon Pay",
      "best_card_discount": 74,
      "coupon": "2% off",
      "coupon_num": 49,
      "emi_savings": "₹81 EMI interest savings",
      "score": 20,
      "rating": 5.0,
      "affiliate_link": "https://www.amazon.in/dp/B0CGPVF1LQ?tag=techeasy0d1-21&linkCode=ll1&linkId=B0CGPVF1LQ&ref_=as_li_ss_tl",
      "posted_at": "2026-05-08T01:02:33.192803+00:00"
    },
    {
      "asin": "B0GMQQ2F15",
      "title": "Toreto Allure Women Smartwatch with 1.27\" IPS Display, Bluetooth Calling, Wireless Charging, Health &amp; Fitness Tracking, IP65 Water Resistant, Smart Notifications – Compatible with HryFine App",
      "price": "₹1,999",
      "price_num": 1999,
      "original_price": "₹20,999",
      "discount_pct": 90,
      "effective_price": "₹1,499",
      "image_url": "https://m.media-amazon.com/images/I/61HhE3TSFeL._SL1000_.jpg",
      "category": "⚡ Electronics",
      "source": "amazon",
      "is_lowest_ever": false,
      "lowest_ever": "₹1,799",
      "average_price": "₹1,949",
      "highest_price": "₹1,999",
      "vs_avg_str": "2% above avg (avg ₹1,949)",
      "vs_avg_pct": -2,
      "best_card_label": "₹500 off via select Credit",
      "best_card_discount": 500,
      "coupon": null,
      "coupon_num": 0,
      "emi_savings": "₹52 EMI interest savings",
      "score": 20,
      "rating": 4.9,
      "affiliate_link": "https://www.amazon.in/dp/B0GMQQ2F15?tag=techeasy0d1-21&linkCode=ll1&linkId=B0GMQQ2F15&ref_=as_li_ss_tl",
      "posted_at": "2026-05-08T01:02:28.278297+00:00"
    },
    {
      "asin": "B09HZLRVGK",
      "title": "Kids Headphones for School with Microphone New bee KH20 HD Stereo Safe Volume Limited 85dB/94dB Foldable Lightweight On-Ear Headphone for PC/Mac/Android/Kindle/Tablet/Pad (Pink)",
      "price": "₹2,698",
      "price_num": 2698,
      "original_price": "₹6,500",
      "discount_pct": 58,
      "effective_price": "₹2,618",
      "image_url": "https://m.media-amazon.com/images/I/716QR4uv-sL._SL1500_.jpg",
      "category": "⚡ Electronics",
      "source": "amazon",
      "is_lowest_ever": false,
      "lowest_ever": null,
      "average_price": null,
      "highest_price": null,
      "vs_avg_str": null,
      "vs_avg_pct": null,
      "best_card_label": "₹80 off via Amazon Pay",
      "best_card_discount": 80,
      "coupon": null,
      "coupon_num": 0,
      "emi_savings": "₹87 EMI interest savings",
      "score": 20,
      "rating": 4.6,
      "affiliate_link": "https://www.amazon.in/dp/B09HZLRVGK?tag=techeasy0d1-21&linkCode=ll1&linkId=B09HZLRVGK&ref_=as_li_ss_tl",
      "posted_at": "2026-05-08T01:02:21.143479+00:00"
    },
    {
      "asin": "B0F4WWCMNK",
      "title": "Midea 563L Side By Side Frost Free Refrigerator",
      "price": "₹44,990",
      "price_num": 44990,
      "original_price": "₹1,19,999",
      "discount_pct": 62,
      "effective_price": null,
      "image_url": "",
      "category": "⚡ Electronics",
      "source": "amazon",
      "is_lowest_ever": false,
      "lowest_ever": "₹42,990",
      "average_price": "₹47,258",
      "highest_price": "₹68,825",
      "vs_avg_str": "4% below avg (avg ₹47,258)",
      "vs_avg_pct": 4,
      "best_card_label": null,
      "best_card_discount": 0,
      "coupon": null,
      "coupon_num": 0,
      "emi_savings": null,
      "score": 24,
      "rating": 4.1,
      "affiliate_link": "https://www.amazon.in/dp/B0F4WWCMNK?tag=techeasy0d1-21&linkCode=ll1&linkId=B0F4WWCMNK&ref_=as_li_ss_tl",
      "posted_at": "2026-05-08T01:02:15.559335+00:00"
    },
    {
      "asin": "B09NLK5YW9",
      "title": "Vilsaw Smart Watch, Fitness Smartwatch with Heart Rate Monitor &amp; Sleep Monitor Health and Fitness Tracker with SpO2 Compatible with iPhone and Android Phones",
      "price": "₹3,295",
      "price_num": 3295,
      "original_price": "₹19,999",
      "discount_pct": 83,
      "effective_price": "₹3,197",
      "image_url": "https://m.media-amazon.com/images/I/617Gs0jZJuL._SL1500_.jpg",
      "category": "⚡ Electronics",
      "source": "amazon",
      "is_lowest_ever": false,
      "lowest_ever": "₹3,246",
      "average_price": "₹5,133",
      "highest_price": "₹9,820",
      "vs_avg_str": "35% below avg (avg ₹5,133)",
      "vs_avg_pct": 35,
      "best_card_label": "₹98 off via Amazon Pay",
      "best_card_discount": 98,
      "coupon": null,
      "coupon_num": 0,
      "emi_savings": "₹85 EMI interest savings",
      "score": 50,
      "rating": 4.8,
      "affiliate_link": "https://www.amazon.in/dp/B09NLK5YW9?tag=techeasy0d1-21&linkCode=ll1&linkId=B09NLK5YW9&ref_=as_li_ss_tl",
      "posted_at": "2026-05-08T01:02:09.042967+00:00"
    },
    {
      "asin": "B0GNC9613C",
      "title": "Omeron® 1 Year Warranty Kids Instant Print Camera 12MP HD Photo &amp; Video, Built-in Thermal Printer, Rechargeable Battery, Fun Filters &amp; Paper Rolls, Educational Gift Toy – Pink",
      "price": "₹1,999",
      "price_num": 1999,
      "original_price": "₹7,999",
      "discount_pct": 75,
      "effective_price": "₹1,940",
      "image_url": "https://m.media-amazon.com/images/I/61XY19ktaOL._SL1000_.jpg",
      "category": "⚡ Electronics",
      "source": "amazon",
      "is_lowest_ever": true,
      "lowest_ever": "₹1,999",
      "average_price": "₹1,999",
      "highest_price": "₹1,999",
      "vs_avg_str": "0% above avg (avg ₹1,999)",
      "vs_avg_pct": 0,
      "best_card_label": "₹59 off via Amazon Pay",
      "best_card_discount": 59,
      "coupon": null,
      "coupon_num": 0,
      "emi_savings": "₹64 EMI interest savings",
      "score": 60,
      "rating": 4.6,
      "affiliate_link": "https://www.amazon.in/dp/B0GNC9613C?tag=techeasy0d1-21&linkCode=ll1&linkId=B0GNC9613C&ref_=as_li_ss_tl",
      "posted_at": "2026-05-08T01:02:01.576697+00:00"
    },
    {
      "asin": "B0G6LYM6DY",
      "title": "Philips 164 cm (65 inches) 4K Ultra HD QLED Smart QD-Mini LED Google TV 65MLED610/94",
      "price": "₹53,999",
      "price_num": 53999,
      "original_price": "₹1,69,990",
      "discount_pct": 68,
      "effective_price": "₹52,249",
      "image_url": "https://m.media-amazon.com/images/I/81b5WyRiUnL._SL1500_.jpg",
      "category": "⚡ Electronics",
      "source": "desidime",
      "is_lowest_ever": true,
      "lowest_ever": "₹53,999",
      "average_price": "₹54,726",
      "highest_price": "₹59,999",
      "vs_avg_str": "1% below avg (avg ₹54,726)",
      "vs_avg_pct": 1,
      "best_card_label": "₹1,750 off via HDFC",
      "best_card_discount": 1750,
      "coupon": null,
      "coupon_num": 0,
      "emi_savings": "₹4,238 EMI interest savings",
      "score": 62,
      "rating": 4.4,
      "affiliate_link": "https://www.amazon.in/dp/B0G6LYM6DY?tag=techeasy0d1-21&linkCode=ll1&linkId=B0G6LYM6DY&ref_=as_li_ss_tl",
      "posted_at": "2026-05-08T01:01:53.629982+00:00"
    },
    {
      "asin": "B071ZJD9SV",
      "title": "VTech Kidizoom Smartwatch DX2 Blue (Frustration Free Packaging)",
      "price": "₹11,047",
      "price_num": 11047,
      "original_price": "₹21,900",
      "discount_pct": 49,
      "effective_price": "₹9,943",
      "image_url": "https://m.media-amazon.com/images/I/81FbghVRGbL._SL1500_.jpg",
      "category": "⚡ Electronics",
      "source": "amazon",
      "is_lowest_ever": true,
      "lowest_ever": "₹11,339",
      "average_price": "₹11,405",
      "highest_price": "₹11,449",
      "vs_avg_str": "3% below avg (avg ₹11,405)",
      "vs_avg_pct": 3,
      "best_card_label": "₹1,104 off via select Credit",
      "best_card_discount": 1104,
      "coupon": null,
      "coupon_num": 0,
      "emi_savings": "₹288 EMI interest savings",
      "score": 64,
      "rating": 4.5,
      "affiliate_link": "https://www.amazon.in/dp/B071ZJD9SV?tag=techeasy0d1-21&linkCode=ll1&linkId=B071ZJD9SV&ref_=as_li_ss_tl",
      "posted_at": "2026-05-08T01:01:45.774874+00:00"
    },
    {
      "asin": "B0GKFHKDKD",
      "title": "GOBOULT Newly Launched Drift2 Smart Watch 1.83'' HD Display,15 Days Battery Life, 150+Watchfaces, 500 Nits Brightness, AI Voice Assistant, SpO2 Monitoring (Carbon Black) (Storm Grey)",
      "price": "₹1,099",
      "price_num": 1099,
      "original_price": "₹19,999",
      "discount_pct": 94,
      "effective_price": null,
      "image_url": "https://m.media-amazon.com/images/I/71A4mgph38L._SL1500_.jpg",
      "category": "⚡ Electronics",
      "source": "amazon",
      "is_lowest_ever": true,
      "lowest_ever": "₹1,099",
      "average_price": "₹2,040",
      "highest_price": "₹8,999",
      "vs_avg_str": "46% below avg (avg ₹2,040)",
      "vs_avg_pct": 46,
      "best_card_label": "₹32 off via Amazon Pay",
      "best_card_discount": 32,
      "coupon": null,
      "coupon_num": 0,
      "emi_savings": null,
      "score": 90,
      "rating": 5.0,
      "affiliate_link": "https://www.amazon.in/dp/B0GKFHKDKD?tag=techeasy0d1-21&linkCode=ll1&linkId=B0GKFHKDKD&ref_=as_li_ss_tl",
      "posted_at": "2026-05-08T01:01:38.253558+00:00"
    },
    {
      "asin": "B0F4WVW7D9",
      "title": "Midea 560 L Side by Side Frost Free Refrigerator",
      "price": "₹44,990",
      "price_num": 44990,
      "original_price": "₹1,28,499",
      "discount_pct": 64,
      "effective_price": "₹41,990",
      "image_url": "https://m.media-amazon.com/images/I/71iB8o2vqlL._SL1500_.jpg",
      "category": "⚡ Electronics",
      "source": "amazon",
      "is_lowest_ever": false,
      "lowest_ever": "₹39,990",
      "average_price": "₹48,937",
      "highest_price": "₹75,900",
      "vs_avg_str": "8% below avg (avg ₹48,937)",
      "vs_avg_pct": 8,
      "best_card_label": "₹3,000 off via HDFC",
      "best_card_discount": 3000,
      "coupon": null,
      "coupon_num": 0,
      "emi_savings": "₹4,517 EMI interest savings",
      "score": 31,
      "rating": 4.1,
      "affiliate_link": "https://www.amazon.in/dp/B0F4WVW7D9?tag=techeasy0d1-21&linkCode=ll1&linkId=B0F4WVW7D9&ref_=as_li_ss_tl",
      "posted_at": "2026-05-08T00:30:49.261043+00:00"
    },
    {
      "asin": "B0D1GJ5TSC",
      "title": "LEONARD USA 52 L Inverter Mini Fridge/Wine Chiller with Toughened Glass Door with UV-Protection l LED Interior Light l Temperature Control for Home Bars (Based on American Technology) (Black)",
      "price": "₹22,990",
      "price_num": 22990,
      "original_price": "₹47,990",
      "discount_pct": 52,
      "effective_price": "₹21,240",
      "image_url": "https://m.media-amazon.com/images/I/71uH5YjiAcL._SL1277_.jpg",
      "category": "⚡ Electronics",
      "source": "amazon",
      "is_lowest_ever": true,
      "lowest_ever": "₹22,990",
      "average_price": "₹22,990",
      "highest_price": "₹22,990",
      "vs_avg_str": "0% above avg (avg ₹22,990)",
      "vs_avg_pct": 0,
      "best_card_label": "₹1,750 off via select Credit",
      "best_card_discount": 1750,
      "coupon": null,
      "coupon_num": 0,
      "emi_savings": "₹1,283 EMI interest savings",
      "score": 61,
      "rating": 5.0,
      "affiliate_link": "https://www.amazon.in/dp/B0D1GJ5TSC?tag=techeasy0d1-21&linkCode=ll1&linkId=B0D1GJ5TSC&ref_=as_li_ss_tl",
      "posted_at": "2026-05-08T00:30:41.615297+00:00"
    },
    {
      "asin": "B0F7HN2RFS",
      "title": "Drumstone 𝐁𝐮𝐲 𝟏 𝐆𝐞𝐭 𝟏 Mini Electric Shaver for Men, Rechargeable Beard Trimmer for Bald, Fade, Vintage Styles, and On-the-Go Grooming with 4 Guide Combs 𝟏𝟓 𝐘𝐞𝐚𝐫𝐬 𝐖𝐚𝐫𝐫𝐚𝐧𝐭𝐲",
      "price": "₹1,299",
      "price_num": 1299,
      "original_price": "₹2,999",
      "discount_pct": 56,
      "effective_price": null,
      "image_url": "https://m.media-amazon.com/images/I/5180tw4eZZL._SL1000_.jpg",
      "category": "🔥 Hot Deal",
      "source": "amazon",
      "is_lowest_ever": false,
      "lowest_ever": "₹939",
      "average_price": "₹1,150",
      "highest_price": "₹1,299",
      "vs_avg_str": "12% above avg (avg ₹1,150)",
      "vs_avg_pct": -12,
      "best_card_label": null,
      "best_card_discount": 0,
      "coupon": null,
      "coupon_num": 0,
      "emi_savings": null,
      "score": 20,
      "rating": 5.0,
      "affiliate_link": "https://www.amazon.in/dp/B0F7HN2RFS?tag=techeasy0d1-21&linkCode=ll1&linkId=B0F7HN2RFS&ref_=as_li_ss_tl",
      "posted_at": "2026-05-08T00:08:22.526898+00:00"
    },
    {
      "asin": "B0CPBPZFBV",
      "title": "Buy Classic Essentials Combo Pack of Triply 24 cm Frypan and &amp; 1 Triply Inner Lid 5 L Pressure Cooker",
      "price": "₹2,999",
      "price_num": 2999,
      "original_price": "₹6,965",
      "discount_pct": 56,
      "effective_price": "₹2,910",
      "image_url": "https://m.media-amazon.com/images/I/41BedKqEWSL._SL1000_.jpg",
      "category": "🍳 Kitchen",
      "source": "amazon",
      "is_lowest_ever": false,
      "lowest_ever": null,
      "average_price": null,
      "highest_price": null,
      "vs_avg_str": null,
      "vs_avg_pct": null,
      "best_card_label": "₹89 off via Amazon Pay",
      "best_card_discount": 89,
      "coupon": null,
      "coupon_num": 0,
      "emi_savings": "₹97 EMI interest savings",
      "score": 20,
      "rating": 5.0,
      "affiliate_link": "https://www.amazon.in/dp/B0CPBPZFBV?tag=techeasy0d1-21&linkCode=ll1&linkId=B0CPBPZFBV&ref_=as_li_ss_tl",
      "posted_at": "2026-05-08T00:08:16.689991+00:00"
    },
    {
      "asin": "B09MLZ8GGM",
      "title": "Pioneer Rubber",
      "price": "₹599",
      "price_num": 599,
      "original_price": "₹2,995",
      "discount_pct": 80,
      "effective_price": null,
      "image_url": "https://m.media-amazon.com/images/I/61-9NYh3ZZL._SL1000_.jpg",
      "category": "🔥 Hot Deal",
      "source": "amazon",
      "is_lowest_ever": false,
      "lowest_ever": null,
      "average_price": null,
      "highest_price": null,
      "vs_avg_str": null,
      "vs_avg_pct": null,
      "best_card_label": "₹17 off via Amazon Pay",
      "best_card_discount": 17,
      "coupon": null,
      "coupon_num": 0,
      "emi_savings": null,
      "score": 20,
      "rating": 3.8,
      "affiliate_link": "https://www.amazon.in/dp/B09MLZ8GGM?tag=techeasy0d1-21&linkCode=ll1&linkId=B09MLZ8GGM&ref_=as_li_ss_tl",
      "posted_at": "2026-05-08T00:08:08.959165+00:00"
    },
    {
      "asin": "B081GFLM2M",
      "title": "Buy Alamic Replacement Float Valve for Fagor LUX Multi-Cooker Electric Pressure Cooker - 670041880 Online at Low Prices in India - Amazon.in",
      "price": "₹1,711",
      "price_num": 1711,
      "original_price": "₹20,999",
      "discount_pct": 91,
      "effective_price": "₹1,660",
      "image_url": "https://m.media-amazon.com/images/I/51FrrRFAWdL._SL1000_.jpg",
      "category": "🍳 Kitchen",
      "source": "amazon",
      "is_lowest_ever": false,
      "lowest_ever": null,
      "average_price": null,
      "highest_price": null,
      "vs_avg_str": null,
      "vs_avg_pct": null,
      "best_card_label": "₹51 off via Amazon Pay",
      "best_card_discount": 51,
      "coupon": null,
      "coupon_num": 0,
      "emi_savings": "₹55 EMI interest savings",
      "score": 20,
      "rating": 4.4,
      "affiliate_link": "https://www.amazon.in/dp/B081GFLM2M?tag=techeasy0d1-21&linkCode=ll1&linkId=B081GFLM2M&ref_=as_li_ss_tl",
      "posted_at": "2026-05-08T00:08:01.346183+00:00"
    },
    {
      "asin": "B00DQGTLKA",
      "title": "Buy Silit 2150162100 Spare Part Pressure Cooker Sicomatic Silicone Rubber Ring, 22 cm Online at Low Prices in India - Amazon.in",
      "price": "₹2,924",
      "price_num": 2924,
      "original_price": "₹9,466",
      "discount_pct": 69,
      "effective_price": "₹2,837",
      "image_url": "https://m.media-amazon.com/images/I/51MmO9FPe0L._SL1500_.jpg",
      "category": "🍳 Kitchen",
      "source": "amazon",
      "is_lowest_ever": false,
      "lowest_ever": null,
      "average_price": null,
      "highest_price": null,
      "vs_avg_str": null,
      "vs_avg_pct": null,
      "best_card_label": "₹87 off via Amazon Pay",
      "best_card_discount": 87,
      "coupon": null,
      "coupon_num": 0,
      "emi_savings": "₹94 EMI interest savings",
      "score": 20,
      "rating": 4.7,
      "affiliate_link": "https://www.amazon.in/dp/B00DQGTLKA?tag=techeasy0d1-21&linkCode=ll1&linkId=B00DQGTLKA&ref_=as_li_ss_tl",
      "posted_at": "2026-05-08T00:07:54.313110+00:00"
    },
    {
      "asin": "B0BPHW88S2",
      "title": "Skala Nitrile Rubber Gasket Compatible with 5 Litres Inner-Lid Pressure Cooker",
      "price": "₹399",
      "price_num": 399,
      "original_price": "₹1,499",
      "discount_pct": 73,
      "effective_price": null,
      "image_url": "https://m.media-amazon.com/images/I/51VPj+X4lpL._SL1089_.jpg",
      "category": "🍳 Kitchen",
      "source": "amazon",
      "is_lowest_ever": false,
      "lowest_ever": null,
      "average_price": null,
      "highest_price": null,
      "vs_avg_str": null,
      "vs_avg_pct": null,
      "best_card_label": "₹11 off via Amazon Pay",
      "best_card_discount": 11,
      "coupon": null,
      "coupon_num": 0,
      "emi_savings": null,
      "score": 20,
      "rating": 4.5,
      "affiliate_link": "https://www.amazon.in/dp/B0BPHW88S2?tag=techeasy0d1-21&linkCode=ll1&linkId=B0BPHW88S2&ref_=as_li_ss_tl",
      "posted_at": "2026-05-08T00:07:46.883631+00:00"
    },
    {
      "asin": "B09DT1TM9Q",
      "title": "Hisense 7.0 Kg Fully-Automatic Front Loading Washing Machine",
      "price": "₹27,990",
      "price_num": 27990,
      "original_price": "₹48,500",
      "discount_pct": 42,
      "effective_price": null,
      "image_url": "https://m.media-amazon.com/images/I/614PWgHs2rL._SL1500_.jpg",
      "category": "⚡ Electronics",
      "source": "desidime",
      "is_lowest_ever": false,
      "lowest_ever": "₹17,990",
      "average_price": "₹24,195",
      "highest_price": "₹24,990",
      "vs_avg_str": "15% above avg (avg ₹24,195)",
      "vs_avg_pct": -15,
      "best_card_label": null,
      "best_card_discount": 0,
      "coupon": null,
      "coupon_num": 0,
      "emi_savings": null,
      "score": 20,
      "rating": 3.5,
      "affiliate_link": "https://www.amazon.in/dp/B09DT1TM9Q?tag=techeasy0d1-21&linkCode=ll1&linkId=B09DT1TM9Q&ref_=as_li_ss_tl",
      "posted_at": "2026-05-08T00:07:41.524400+00:00"
    },
    {
      "asin": "B07Y752K2W",
      "title": "Butterfly Cute SS Induction Compatible Pressure Cooker",
      "price": "₹1,595",
      "price_num": 1595,
      "original_price": "₹7,800",
      "discount_pct": 79,
      "effective_price": null,
      "image_url": "https://m.media-amazon.com/images/I/61nRZIWWgcL._SL1500_.jpg",
      "category": "🍳 Kitchen",
      "source": "amazon",
      "is_lowest_ever": false,
      "lowest_ever": "₹1,400",
      "average_price": "₹1,624",
      "highest_price": "₹1,999",
      "vs_avg_str": "1% below avg (avg ₹1,624)",
      "vs_avg_pct": 1,
      "best_card_label": "₹47 off via Amazon Pay",
      "best_card_discount": 47,
      "coupon": null,
      "coupon_num": 0,
      "emi_savings": "₹51 EMI interest savings",
      "score": 21,
      "rating": 4.1,
      "affiliate_link": "https://www.amazon.in/dp/B07Y752K2W?tag=techeasy0d1-21&linkCode=ll1&linkId=B07Y752K2W&ref_=as_li_ss_tl",
      "posted_at": "2026-05-08T00:07:36.638931+00:00"
    },
    {
      "asin": "B09NMM5YQY",
      "title": "Florix Autoclave 12 * 12 Approx 22 to 23 liter Almunium finish Autoclave Pressure cooker type A1 quality Dental Automatic Autoclave",
      "price": "₹6,390",
      "price_num": 6390,
      "original_price": "₹14,999",
      "discount_pct": 57,
      "effective_price": "₹5,390",
      "image_url": "",
      "category": "🍳 Kitchen",
      "source": "amazon",
      "is_lowest_ever": false,
      "lowest_ever": null,
      "average_price": null,
      "highest_price": null,
      "vs_avg_str": null,
      "vs_avg_pct": null,
      "best_card_label": "₹1,000 off via select Credit",
      "best_card_discount": 1000,
      "coupon": null,
      "coupon_num": 0,
      "emi_savings": "₹207 EMI interest savings",
      "score": 21,
      "rating": 5.0,
      "affiliate_link": "https://www.amazon.in/dp/B09NMM5YQY?tag=techeasy0d1-21&linkCode=ll1&linkId=B09NMM5YQY&ref_=as_li_ss_tl",
      "posted_at": "2026-05-08T00:07:29.142998+00:00"
    },
    {
      "asin": "B0BSNR1V9N",
      "title": "GREENCHEF Shine Stainless Steel Pressure Cooker",
      "price": "₹1,099",
      "price_num": 1099,
      "original_price": "₹5,099",
      "discount_pct": 78,
      "effective_price": null,
      "image_url": "https://m.media-amazon.com/images/I/61fddCbEwLL._SL1500_.jpg",
      "category": "🍳 Kitchen",
      "source": "amazon",
      "is_lowest_ever": false,
      "lowest_ever": "₹890",
      "average_price": "₹1,273",
      "highest_price": "₹2,850",
      "vs_avg_str": "13% below avg (avg ₹1,273)",
      "vs_avg_pct": 13,
      "best_card_label": "₹32 off via Amazon Pay",
      "best_card_discount": 32,
      "coupon": null,
      "coupon_num": 0,
      "emi_savings": null,
      "score": 33,
      "rating": 4.1,
      "affiliate_link": "https://www.amazon.in/dp/B0BSNR1V9N?tag=techeasy0d1-21&linkCode=ll1&linkId=B0BSNR1V9N&ref_=as_li_ss_tl",
      "posted_at": "2026-05-08T00:07:22.615226+00:00"
    },
    {
      "asin": "B071G1RLYC",
      "title": "eKids Spiderman Wireless Headphones Over Ear Headphone with Mic (Multicolour)",
      "price": "₹4,192",
      "price_num": 4192,
      "original_price": "₹25,799",
      "discount_pct": 83,
      "effective_price": "₹3,192",
      "image_url": "https://m.media-amazon.com/images/I/71hJZGWOeCL._SL1500_.jpg",
      "category": "⚡ Electronics",
      "source": "amazon",
      "is_lowest_ever": false,
      "lowest_ever": "₹3,601",
      "average_price": "₹5,398",
      "highest_price": "₹9,391",
      "vs_avg_str": "22% below avg (avg ₹5,398)",
      "vs_avg_pct": 22,
      "best_card_label": "₹1,000 off via select Credit",
      "best_card_discount": 1000,
      "coupon": null,
      "coupon_num": 0,
      "emi_savings": "₹135 EMI interest savings",
      "score": 43,
      "rating": 4.6,
      "affiliate_link": "https://www.amazon.in/dp/B071G1RLYC?tag=techeasy0d1-21&linkCode=ll1&linkId=B071G1RLYC&ref_=as_li_ss_tl",
      "posted_at": "2026-05-08T00:07:17.118041+00:00"
    },
    {
      "asin": "B0FWC4Q9FN",
      "title": "Buy Lifelong 2 Litre Triply Stainless Steel Pressure Cooker for Kitchen",
      "price": "₹1,399",
      "price_num": 1399,
      "original_price": "₹7,800",
      "discount_pct": 82,
      "effective_price": null,
      "image_url": "https://m.media-amazon.com/images/I/614b7qgpQRL._SL1500_.jpg",
      "category": "🍳 Kitchen",
      "source": "amazon",
      "is_lowest_ever": true,
      "lowest_ever": "₹1,499",
      "average_price": "₹1,499",
      "highest_price": "₹1,499",
      "vs_avg_str": "6% below avg (avg ₹1,499)",
      "vs_avg_pct": 6,
      "best_card_label": "₹41 off via Amazon Pay",
      "best_card_discount": 41,
      "coupon": null,
      "coupon_num": 0,
      "emi_savings": null,
      "score": 66,
      "rating": 4.1,
      "affiliate_link": "https://www.amazon.in/dp/B0FWC4Q9FN?tag=techeasy0d1-21&linkCode=ll1&linkId=B0FWC4Q9FN&ref_=as_li_ss_tl",
      "posted_at": "2026-05-08T00:07:07.062007+00:00"
    },
    {
      "asin": "B0GCDCJDTQ",
      "title": "Buy Pigeon All in One Super Cooker Stainless Steel 3 L Induction Bottom Pressure Cooker (Stainless Steel) Online at Low Prices in India - Amazon.in",
      "price": "₹1,959",
      "price_num": 1959,
      "original_price": "₹5,499",
      "discount_pct": 64,
      "effective_price": "₹1,901",
      "image_url": "https://m.media-amazon.com/images/I/71VGtK5AhZL._SL1500_.jpg",
      "category": "🍳 Kitchen",
      "source": "amazon",
      "is_lowest_ever": true,
      "lowest_ever": "₹1,999",
      "average_price": "₹2,579",
      "highest_price": "₹2,899",
      "vs_avg_str": "24% below avg (avg ₹2,579)",
      "vs_avg_pct": 24,
      "best_card_label": "₹58 off via Amazon Pay",
      "best_card_discount": 58,
      "coupon": null,
      "coupon_num": 0,
      "emi_savings": "₹63 EMI interest savings",
      "score": 84,
      "rating": 3.8,
      "affiliate_link": "https://www.amazon.in/dp/B0GCDCJDTQ?tag=techeasy0d1-21&linkCode=ll1&linkId=B0GCDCJDTQ&ref_=as_li_ss_tl",
      "posted_at": "2026-05-08T00:06:59.015927+00:00"
    },
    {
      "asin": "B0CRDBYST8",
      "title": "Buy Vinod Platinum Triply Stainless Steel Pressure Cooker Combo Set of 2-3 &amp; 2 Litre",
      "price": "₹2,527",
      "price_num": 2527,
      "original_price": "₹7,800",
      "discount_pct": 67,
      "effective_price": "₹2,452",
      "image_url": "https://m.media-amazon.com/images/I/61GtbZISwbL._SL1500_.jpg",
      "category": "🍳 Kitchen",
      "source": "amazon",
      "is_lowest_ever": true,
      "lowest_ever": "₹3,999",
      "average_price": "₹4,772",
      "highest_price": "₹6,470",
      "vs_avg_str": "47% below avg (avg ₹4,772)",
      "vs_avg_pct": 47,
      "best_card_label": "₹75 off via Amazon Pay",
      "best_card_discount": 75,
      "coupon": null,
      "coupon_num": 0,
      "emi_savings": "₹81 EMI interest savings",
      "score": 90,
      "rating": 4.1,
      "affiliate_link": "https://www.amazon.in/dp/B0CRDBYST8?tag=techeasy0d1-21&linkCode=ll1&linkId=B0CRDBYST8&ref_=as_li_ss_tl",
      "posted_at": "2026-05-08T00:06:51.626153+00:00"
    },
    {
      "asin": "B0DCZ51G2H",
      "title": "TheGiftKart Rugged Carbon Fibre Armor Back Cover Case for Google Pixel 9/9 Pro",
      "price": "₹299",
      "price_num": 299,
      "original_price": "₹999",
      "discount_pct": 70,
      "effective_price": null,
      "image_url": "",
      "category": "🔥 Hot Deal",
      "source": "amazon",
      "is_lowest_ever": false,
      "lowest_ever": "₹285",
      "average_price": "₹295",
      "highest_price": "₹301",
      "vs_avg_str": "1% above avg (avg ₹295)",
      "vs_avg_pct": -1,
      "best_card_label": null,
      "best_card_discount": 0,
      "coupon": null,
      "coupon_num": 0,
      "emi_savings": null,
      "score": 20,
      "rating": 4.5,
      "affiliate_link": "https://www.amazon.in/dp/B0DCZ51G2H?tag=techeasy0d1-21&linkCode=ll1&linkId=B0DCZ51G2H&ref_=as_li_ss_tl",
      "posted_at": "2026-05-07T23:37:33.372718+00:00"
    },
    {
      "asin": "B0BRQ7PZG4",
      "title": "Glynzak Wireless Bluetooth Headphones Over Ear - 65H Playtime HiFi Stereo Headset with Microphone and 6EQ Modes Foldable Bluetooth V5.3 Headphones for Travel Smartphone Computer Laptop (Black Red)",
      "price": "₹3,670",
      "price_num": 3670,
      "original_price": "₹13,683",
      "discount_pct": 73,
      "effective_price": null,
      "image_url": "",
      "category": "⚡ Electronics",
      "source": "amazon",
      "is_lowest_ever": false,
      "lowest_ever": "₹2,869",
      "average_price": "₹5,128",
      "highest_price": "₹8,532",
      "vs_avg_str": "28% below avg (avg ₹5,128)",
      "vs_avg_pct": 28,
      "best_card_label": null,
      "best_card_discount": 0,
      "coupon": null,
      "coupon_num": 0,
      "emi_savings": null,
      "score": 48,
      "rating": 4.6,
      "affiliate_link": "https://www.amazon.in/dp/B0BRQ7PZG4?tag=techeasy0d1-21&linkCode=ll1&linkId=B0BRQ7PZG4&ref_=as_li_ss_tl",
      "posted_at": "2026-05-07T23:37:26.073772+00:00"
    },
    {
      "asin": "B07SBR4C8Z",
      "title": "Buy ACTIVA 10L Storage Water Heater Geyser",
      "price": "₹3,199",
      "price_num": 3199,
      "original_price": "₹14,399",
      "discount_pct": 77,
      "effective_price": "₹3,104",
      "image_url": "https://m.media-amazon.com/images/I/61rx8UbLvQL._SL1500_.jpg",
      "category": "🔥 Hot Deal",
      "source": "amazon",
      "is_lowest_ever": false,
      "lowest_ever": "₹2,652",
      "average_price": "₹3,009",
      "highest_price": "₹3,316",
      "vs_avg_str": "6% above avg (avg ₹3,009)",
      "vs_avg_pct": -6,
      "best_card_label": "₹95 off via Amazon Pay",
      "best_card_discount": 95,
      "coupon": null,
      "coupon_num": 0,
      "emi_savings": "₹103 EMI interest savings",
      "score": 20,
      "rating": 4.3,
      "affiliate_link": "https://www.amazon.in/dp/B07SBR4C8Z?tag=techeasy0d1-21&linkCode=ll1&linkId=B07SBR4C8Z&ref_=as_li_ss_tl",
      "posted_at": "2026-05-07T23:16:13.364535+00:00"
    },
    {
      "asin": "B00BWSB2P6",
      "title": "Alen (BF35) HEPA-Pure Replacement Filter for BreatheSmart Air Purifier, 1-Pack",
      "price": "₹12,359",
      "price_num": 12359,
      "original_price": "₹46,133",
      "discount_pct": 73,
      "effective_price": null,
      "image_url": "",
      "category": "🔥 Hot Deal",
      "source": "amazon",
      "is_lowest_ever": false,
      "lowest_ever": null,
      "average_price": null,
      "highest_price": null,
      "vs_avg_str": null,
      "vs_avg_pct": null,
      "best_card_label": null,
      "best_card_discount": 0,
      "coupon": null,
      "coupon_num": 0,
      "emi_savings": null,
      "score": 20,
      "rating": 4.7,
      "affiliate_link": "https://www.amazon.in/dp/B00BWSB2P6?tag=techeasy0d1-21&linkCode=ll1&linkId=B00BWSB2P6&ref_=as_li_ss_tl",
      "posted_at": "2026-05-07T23:16:06.401847+00:00"
    },
    {
      "asin": "B00C9F0G9E",
      "title": "Alen (TF15) HEPA-Pure Replacement Filter for T100 and T300 Air Purifiers, 1-Pack (set of 2 filters)",
      "price": "₹11,092",
      "price_num": 11092,
      "original_price": "₹34,900",
      "discount_pct": 68,
      "effective_price": "₹9,983",
      "image_url": "https://m.media-amazon.com/images/I/81FlSTy6MNL._SL1500_.jpg",
      "category": "🔥 Hot Deal",
      "source": "amazon",
      "is_lowest_ever": false,
      "lowest_ever": null,
      "average_price": null,
      "highest_price": null,
      "vs_avg_str": null,
      "vs_avg_pct": null,
      "best_card_label": "₹1,109 off via select Credit",
      "best_card_discount": 1109,
      "coupon": null,
      "coupon_num": 0,
      "emi_savings": "₹359 EMI interest savings",
      "score": 21,
      "rating": 4.6,
      "affiliate_link": "https://www.amazon.in/dp/B00C9F0G9E?tag=techeasy0d1-21&linkCode=ll1&linkId=B00C9F0G9E&ref_=as_li_ss_tl",
      "posted_at": "2026-05-07T23:15:58.894437+00:00"
    },
    {
      "asin": "B0FBLWVRCV",
      "title": "Buy Havells All New Adonia Spin 10L 5 Star Storage Water Heater(Geyser)",
      "price": "₹9,490",
      "price_num": 9490,
      "original_price": "₹28,999",
      "discount_pct": 67,
      "effective_price": "₹8,490",
      "image_url": "https://m.media-amazon.com/images/I/61Yb9QMhGpL._SL1500_.jpg",
      "category": "🔥 Hot Deal",
      "source": "amazon",
      "is_lowest_ever": false,
      "lowest_ever": "₹6,925",
      "average_price": "₹8,745",
      "highest_price": "₹10,490",
      "vs_avg_str": "8% above avg (avg ₹8,745)",
      "vs_avg_pct": -8,
      "best_card_label": "₹1,000 off via select Credit",
      "best_card_discount": 1000,
      "coupon": null,
      "coupon_num": 0,
      "emi_savings": "₹952 EMI interest savings",
      "score": 21,
      "rating": 4.3,
      "affiliate_link": "https://www.amazon.in/dp/B0FBLWVRCV?tag=techeasy0d1-21&linkCode=ll1&linkId=B0FBLWVRCV&ref_=as_li_ss_tl",
      "posted_at": "2026-05-07T23:15:53.753531+00:00"
    },
    {
      "asin": "B0GPZVGTQG",
      "title": "PurePlus 50 Liter Commercial RO Water Purifier Plant with TDS Adjuster Blue Stainless steel Full Automatic with TDS Adjuster",
      "price": "₹11,499",
      "price_num": 11499,
      "original_price": "₹29,999",
      "discount_pct": 61,
      "effective_price": "₹10,350",
      "image_url": "https://m.media-amazon.com/images/I/71H8SWoaEwL._SL1500_.jpg",
      "category": "🔥 Hot Deal",
      "source": "amazon",
      "is_lowest_ever": false,
      "lowest_ever": "₹10,999",
      "average_price": "₹11,467",
      "highest_price": "₹11,499",
      "vs_avg_str": "0% above avg (avg ₹11,467)",
      "vs_avg_pct": 0,
      "best_card_label": "₹1,149 off via select Credit",
      "best_card_discount": 1149,
      "coupon": null,
      "coupon_num": 0,
      "emi_savings": "₹372 EMI interest savings",
      "score": 21,
      "rating": 4.2,
      "affiliate_link": "https://www.amazon.in/dp/B0GPZVGTQG?tag=techeasy0d1-21&linkCode=ll1&linkId=B0GPZVGTQG&ref_=as_li_ss_tl",
      "posted_at": "2026-05-07T23:15:48.851377+00:00"
    },
    {
      "asin": "B0GPZGQ481",
      "title": "PurePlus 25 LPH Commercial RO Water Purifier with Double Purification, Booster Pump &amp; 3 Stage Pre-Filtration – Heavy Duty Stainless Steel System",
      "price": "₹7,799",
      "price_num": 7799,
      "original_price": "₹24,999",
      "discount_pct": 68,
      "effective_price": "₹6,799",
      "image_url": "https://m.media-amazon.com/images/I/71SjO41CwML._SL1500_.jpg",
      "category": "🔥 Hot Deal",
      "source": "amazon",
      "is_lowest_ever": false,
      "lowest_ever": "₹7,499",
      "average_price": "₹7,776",
      "highest_price": "₹7,799",
      "vs_avg_str": "0% above avg (avg ₹7,776)",
      "vs_avg_pct": 0,
      "best_card_label": "₹1,000 off via select Credit",
      "best_card_discount": 1000,
      "coupon": null,
      "coupon_num": 0,
      "emi_savings": "₹252 EMI interest savings",
      "score": 21,
      "rating": 3.9,
      "affiliate_link": "https://www.amazon.in/dp/B0GPZGQ481?tag=techeasy0d1-21&linkCode=ll1&linkId=B0GPZGQ481&ref_=as_li_ss_tl",
      "posted_at": "2026-05-07T23:15:42.185636+00:00"
    },
    {
      "asin": "B0F3HWJXZ5",
      "title": "TCL 164 cm (65 inches) 4K UHD Smart QD-Mini LED Google TV 65Q6C",
      "price": "₹66,990",
      "price_num": 66990,
      "original_price": "₹1,69,990",
      "discount_pct": 60,
      "effective_price": "₹64,981",
      "image_url": "https://m.media-amazon.com/images/I/818vnFP09yL._SL1500_.jpg",
      "category": "⚡ Electronics",
      "source": "amazon",
      "is_lowest_ever": false,
      "lowest_ever": "₹64,490",
      "average_price": "₹68,035",
      "highest_price": "₹75,401",
      "vs_avg_str": "1% below avg (avg ₹68,035)",
      "vs_avg_pct": 1,
      "best_card_label": "₹2,009 off via Amazon Pay",
      "best_card_discount": 2009,
      "coupon": null,
      "coupon_num": 0,
      "emi_savings": "₹3,740 EMI interest savings",
      "score": 23,
      "rating": 4.1,
      "affiliate_link": "https://www.amazon.in/dp/B0F3HWJXZ5?tag=techeasy0d1-21&linkCode=ll1&linkId=B0F3HWJXZ5&ref_=as_li_ss_tl",
      "posted_at": "2026-05-07T23:15:35.158315+00:00"
    },
    {
      "asin": "B0DF96JGRJ",
      "title": "AquaDart Mineral RO+UV+UF 12 Liter RO + UV + TDS ADJUSTER Water Purifier With Copper Charge Technology Black &amp; Copper Best For Home and Office (Made In India)",
      "price": "₹4,749",
      "price_num": 4749,
      "original_price": "₹24,999",
      "discount_pct": 81,
      "effective_price": "₹3,749",
      "image_url": "https://m.media-amazon.com/images/I/71wOsz5929L._SL1500_.jpg",
      "category": "🏠 Home",
      "source": "amazon",
      "is_lowest_ever": false,
      "lowest_ever": "₹4,699",
      "average_price": "₹4,915",
      "highest_price": "₹4,999",
      "vs_avg_str": "3% below avg (avg ₹4,915)",
      "vs_avg_pct": 3,
      "best_card_label": "₹1,000 off via select Credit",
      "best_card_discount": 1000,
      "coupon": null,
      "coupon_num": 0,
      "emi_savings": "₹154 EMI interest savings",
      "score": 24,
      "rating": 4.7,
      "affiliate_link": "https://www.amazon.in/dp/B0DF96JGRJ?tag=techeasy0d1-21&linkCode=ll1&linkId=B0DF96JGRJ&ref_=as_li_ss_tl",
      "posted_at": "2026-05-07T23:15:27.165130+00:00"
    },
    {
      "asin": "B0G1KX8CMW",
      "title": "iSpring Zinc Copper Alkaline Hydrogen RO Water Purifier",
      "price": "₹5,224",
      "price_num": 5224,
      "original_price": "₹1,12,323",
      "discount_pct": 95,
      "effective_price": "₹4,224",
      "image_url": "https://m.media-amazon.com/images/I/61HNcCwIrmL._SL1500_.jpg",
      "category": "🔥 Hot Deal",
      "source": "amazon",
      "is_lowest_ever": false,
      "lowest_ever": "₹5,199",
      "average_price": "₹5,486",
      "highest_price": "₹5,499",
      "vs_avg_str": "4% below avg (avg ₹5,486)",
      "vs_avg_pct": 4,
      "best_card_label": "₹1,000 off via select Credit",
      "best_card_discount": 1000,
      "coupon": null,
      "coupon_num": 0,
      "emi_savings": "₹169 EMI interest savings",
      "score": 25,
      "rating": 4.7,
      "affiliate_link": "https://www.amazon.in/dp/B0G1KX8CMW?tag=techeasy0d1-21&linkCode=ll1&linkId=B0G1KX8CMW&ref_=as_li_ss_tl",
      "posted_at": "2026-05-07T23:15:20.298199+00:00"
    },
    {
      "asin": "B0D6R19L4F",
      "title": "Buy Colorbot Helix BLDC Ceiling Fans 1200mm",
      "price": "₹2,849",
      "price_num": 2849,
      "original_price": "₹7,089",
      "discount_pct": 59,
      "effective_price": null,
      "image_url": "",
      "category": "🔥 Hot Deal",
      "source": "amazon",
      "is_lowest_ever": false,
      "lowest_ever": "₹2,659",
      "average_price": "₹3,130",
      "highest_price": "₹3,899",
      "vs_avg_str": "8% below avg (avg ₹3,130)",
      "vs_avg_pct": 8,
      "best_card_label": null,
      "best_card_discount": 0,
      "coupon": null,
      "coupon_num": 0,
      "emi_savings": null,
      "score": 28,
      "rating": 4.4,
      "affiliate_link": "https://www.amazon.in/dp/B0D6R19L4F?tag=techeasy0d1-21&linkCode=ll1&linkId=B0D6R19L4F&ref_=as_li_ss_tl",
      "posted_at": "2026-05-07T23:15:14.825175+00:00"
    },
    {
      "asin": "B0FBLXGRXB",
      "title": "Buy Havells All New Bianca+ 10L 5 Star 3-in-1 Convertible Storage Water Heater(Geyser)",
      "price": "₹9,974",
      "price_num": 9974,
      "original_price": "₹22,790",
      "discount_pct": 56,
      "effective_price": "₹8,974",
      "image_url": "https://m.media-amazon.com/images/I/51JqaSdUGxL._SL1500_.jpg",
      "category": "🔥 Hot Deal",
      "source": "amazon",
      "is_lowest_ever": false,
      "lowest_ever": "₹8,500",
      "average_price": "₹11,444",
      "highest_price": "₹12,490",
      "vs_avg_str": "12% below avg (avg ₹11,444)",
      "vs_avg_pct": 12,
      "best_card_label": "₹1,000 off via select Credit",
      "best_card_discount": 1000,
      "coupon": null,
      "coupon_num": 0,
      "emi_savings": "₹323 EMI interest savings",
      "score": 33,
      "rating": 5.0,
      "affiliate_link": "https://www.amazon.in/dp/B0FBLXGRXB?tag=techeasy0d1-21&linkCode=ll1&linkId=B0FBLXGRXB&ref_=as_li_ss_tl",
      "posted_at": "2026-05-07T23:15:07.702593+00:00"
    },
    {
      "asin": "B083NR5DVY",
      "title": "Waterdrop 15Ua Under Sink Water Filter System,16K Gallons Ultra High Capacity Main Faucet Under Counter Water Filtration System,Removes 99% Lead,Fluoride,Chlorine,Bad Taste,Usa Tech,0.5 Micron,White",
      "price": "₹10,165",
      "price_num": 10165,
      "original_price": "₹24,999",
      "discount_pct": 59,
      "effective_price": "₹8,946",
      "image_url": "https://m.media-amazon.com/images/I/61YfVXLGV8L._SL1500_.jpg",
      "category": "🔥 Hot Deal",
      "source": "amazon",
      "is_lowest_ever": false,
      "lowest_ever": "₹7,567",
      "average_price": "₹12,552",
      "highest_price": "₹18,798",
      "vs_avg_str": "19% below avg (avg ₹12,552)",
      "vs_avg_pct": 19,
      "best_card_label": "₹1,016 off via select Credit",
      "best_card_discount": 1016,
      "coupon": "2% off",
      "coupon_num": 203,
      "emi_savings": "₹329 EMI interest savings",
      "score": 40,
      "rating": 4.6,
      "affiliate_link": "https://www.amazon.in/dp/B083NR5DVY?tag=techeasy0d1-21&linkCode=ll1&linkId=B083NR5DVY&ref_=as_li_ss_tl",
      "posted_at": "2026-05-07T23:15:00.202293+00:00"
    },
    {
      "asin": "B00NVLAYX8",
      "title": "Alen Air Filter FF50-Pure Replacement H13 True HEPA Filter for BreatheSmart FIT50 Air Purifier - Captures Allergens, Dust, &amp; Mold (1 Filter)",
      "price": "₹13,556",
      "price_num": 13556,
      "original_price": "₹42,766",
      "discount_pct": 68,
      "effective_price": "₹12,201",
      "image_url": "https://m.media-amazon.com/images/I/61h8rAciSbL._SL1500_.jpg",
      "category": "🔥 Hot Deal",
      "source": "amazon",
      "is_lowest_ever": false,
      "lowest_ever": "₹11,057",
      "average_price": "₹19,586",
      "highest_price": "₹34,695",
      "vs_avg_str": "30% below avg (avg ₹19,586)",
      "vs_avg_pct": 30,
      "best_card_label": "₹1,355 off via select Credit",
      "best_card_discount": 1355,
      "coupon": null,
      "coupon_num": 0,
      "emi_savings": "₹439 EMI interest savings",
      "score": 51,
      "rating": 4.7,
      "affiliate_link": "https://www.amazon.in/dp/B00NVLAYX8?tag=techeasy0d1-21&linkCode=ll1&linkId=B00NVLAYX8&ref_=as_li_ss_tl",
      "posted_at": "2026-05-07T23:14:53.115721+00:00"
    },
    {
      "asin": "B00D8JGOU0",
      "title": "Fellowes AeraMax 290/300/DX95 Purifiers True HEPA Air Filter, 16.3\" x 12.6\" x 1.2\", White",
      "price": "₹5,639",
      "price_num": 5639,
      "original_price": "₹34,900",
      "discount_pct": 83,
      "effective_price": "₹4,639",
      "image_url": "https://m.media-amazon.com/images/I/61Jm4s47cZL._SL1500_.jpg",
      "category": "🔥 Hot Deal",
      "source": "amazon",
      "is_lowest_ever": true,
      "lowest_ever": "₹5,640",
      "average_price": "₹5,640",
      "highest_price": "₹5,640",
      "vs_avg_str": "0% above avg (avg ₹5,640)",
      "vs_avg_pct": 0,
      "best_card_label": "₹1,000 off via select Credit",
      "best_card_discount": 1000,
      "coupon": null,
      "coupon_num": 0,
      "emi_savings": "₹182 EMI interest savings",
      "score": 61,
      "rating": 4.8,
      "affiliate_link": "https://www.amazon.in/dp/B00D8JGOU0?tag=techeasy0d1-21&linkCode=ll1&linkId=B00D8JGOU0&ref_=as_li_ss_tl",
      "posted_at": "2026-05-07T23:14:46.527026+00:00"
    },
    {
      "asin": "B0GVB7C5B9",
      "title": "iSpring 50 LPH Commercial RO Water Purifier Plant with TDS Adjuster 50 Litre Blue Stainless steel Full Automatic with TDS Adjuster",
      "price": "₹10,999",
      "price_num": 10999,
      "original_price": "₹34,499",
      "discount_pct": 68,
      "effective_price": "₹9,900",
      "image_url": "https://m.media-amazon.com/images/I/71byj1ayuuL._SL1500_.jpg",
      "category": "🔥 Hot Deal",
      "source": "amazon",
      "is_lowest_ever": true,
      "lowest_ever": "₹10,999",
      "average_price": "₹10,999",
      "highest_price": "₹10,999",
      "vs_avg_str": "0% above avg (avg ₹10,999)",
      "vs_avg_pct": 0,
      "best_card_label": "₹1,099 off via select Credit",
      "best_card_discount": 1099,
      "coupon": null,
      "coupon_num": 0,
      "emi_savings": "₹356 EMI interest savings",
      "score": 61,
      "rating": 4.6,
      "affiliate_link": "https://www.amazon.in/dp/B0GVB7C5B9?tag=techeasy0d1-21&linkCode=ll1&linkId=B0GVB7C5B9&ref_=as_li_ss_tl",
      "posted_at": "2026-05-07T23:14:40.139393+00:00"
    }
  ]
}