{
  "updated_at": "2026-05-05T20:54:53.120261+00:00",
  "deals": [
    {
      "asin": "B0BLSQVN7Q",
      "title": "Buy ACTIVA Pluto 2 Jar 500 Watts Mixer Grinder Comes With 2 Year Warranty Red &amp; White Online at Low Prices in India - Amazon.in",
      "price": "₹1,249",
      "price_num": 1249,
      "original_price": "₹3,990",
      "discount_pct": 68,
      "effective_price": null,
      "image_url": "https://m.media-amazon.com/images/I/51CNkgQZ+nL._SL1280_.jpg",
      "category": "🍳 Kitchen",
      "source": "amazon",
      "is_lowest_ever": false,
      "lowest_ever": "₹1,099",
      "average_price": "₹1,207",
      "highest_price": "₹1,299",
      "vs_avg_str": "3% above avg (avg ₹1,207)",
      "vs_avg_pct": -3,
      "best_card_label": "₹37 off via Amazon Pay",
      "best_card_discount": 37,
      "coupon": null,
      "coupon_num": 0,
      "emi_savings": null,
      "score": 20,
      "rating": 4.3,
      "affiliate_link": "https://www.amazon.in/dp/B0BLSQVN7Q?tag=techeasy0d1-21&linkCode=ll1&linkId=B0BLSQVN7Q&ref_=as_li_ss_tl",
      "posted_at": "2026-05-05T20:53:34.723284+00:00"
    },
    {
      "asin": "B0GTVSWRL1",
      "title": "Buy Drumstone (𝐄𝐱𝐥𝐮𝐬𝐢𝐯𝐞 𝟐𝟎 𝐘𝐞𝐚𝐫𝐬 𝐰𝐚𝐫𝐫𝐚𝐧𝐭𝐲) Portable 2000W Induction Cooktop Electric Stove,Smart Cooking Menus, Timer Control, Fast Heating, Durable Glass Top for Home Kitchen Use Online at Low Prices in India - Amazon.in",
      "price": "₹2,999",
      "price_num": 2999,
      "original_price": "₹27,990",
      "discount_pct": 89,
      "effective_price": null,
      "image_url": "",
      "category": "🏠 Home",
      "source": "amazon",
      "is_lowest_ever": false,
      "lowest_ever": null,
      "average_price": null,
      "highest_price": null,
      "vs_avg_str": null,
      "vs_avg_pct": null,
      "best_card_label": null,
      "best_card_discount": 0,
      "coupon": null,
      "coupon_num": 0,
      "emi_savings": null,
      "score": 20,
      "rating": 5.0,
      "affiliate_link": "https://www.amazon.in/dp/B0GTVSWRL1?tag=techeasy0d1-21&linkCode=ll1&linkId=B0GTVSWRL1&ref_=as_li_ss_tl",
      "posted_at": "2026-05-05T20:53:30.168287+00:00"
    },
    {
      "asin": "B0GTVMWPFH",
      "title": "Buy Drumstone (𝟐𝟎 𝐘𝐞𝐚𝐫𝐬 𝐰𝐚𝐫𝐫𝐚𝐧𝐭𝐲) 2000W Induction Cooker Portable Electric Stove, Fast Heating Induction Cooktop with Temperature Control,Crystal Glass Surface for Kitchen Online at Low Prices in India - Amazon.in",
      "price": "₹2,999",
      "price_num": 2999,
      "original_price": "₹5,695",
      "discount_pct": 47,
      "effective_price": "₹2,851",
      "image_url": "https://m.media-amazon.com/images/I/71vABEv6f+L._SL1500_.jpg",
      "category": "🍳 Kitchen",
      "source": "amazon",
      "is_lowest_ever": false,
      "lowest_ever": null,
      "average_price": null,
      "highest_price": null,
      "vs_avg_str": null,
      "vs_avg_pct": null,
      "best_card_label": "₹89 off via Amazon Pay",
      "best_card_discount": 89,
      "coupon": "2% off",
      "coupon_num": 59,
      "emi_savings": "₹97 EMI interest savings",
      "score": 20,
      "rating": 5.0,
      "affiliate_link": "https://www.amazon.in/dp/B0GTVMWPFH?tag=techeasy0d1-21&linkCode=ll1&linkId=B0GTVMWPFH&ref_=as_li_ss_tl",
      "posted_at": "2026-05-05T20:53:23.666736+00:00"
    },
    {
      "asin": "B0GWQ2YX1H",
      "title": "Buy Drumstone 𝟏𝟓-𝐘𝐞𝐚𝐫 𝐋𝐨𝐧𝐠-𝐋𝐢𝐟𝐞 𝐖𝐚𝐫𝐫𝐚𝐧𝐭𝐲 Induction Stove 2000W, Electric Cooking Cooktop with Fast Heating, Portable Kitchen Stove for Home Use Online at Low Prices in India - Amazon.in",
      "price": "₹2,999",
      "price_num": 2999,
      "original_price": "₹5,990",
      "discount_pct": 49,
      "effective_price": "₹2,910",
      "image_url": "",
      "category": "🏠 Home",
      "source": "amazon",
      "is_lowest_ever": false,
      "lowest_ever": null,
      "average_price": null,
      "highest_price": null,
      "vs_avg_str": null,
      "vs_avg_pct": null,
      "best_card_label": "₹89 off via Amazon Pay",
      "best_card_discount": 89,
      "coupon": null,
      "coupon_num": 0,
      "emi_savings": "₹97 EMI interest savings",
      "score": 20,
      "rating": 5.0,
      "affiliate_link": "https://www.amazon.in/dp/B0GWQ2YX1H?tag=techeasy0d1-21&linkCode=ll1&linkId=B0GWQ2YX1H&ref_=as_li_ss_tl",
      "posted_at": "2026-05-05T20:53:16.768016+00:00"
    },
    {
      "asin": "B0GTTT2N61",
      "title": "Buy Drumstone (15 Years Replacement Warranty) 2000W Induction Cooktop with Toughened Glass Top, Smart Touch Control Panel, Fast Heating Electric Stove for Efficient Home Cooking Online at Low Prices in India - Amazon.in",
      "price": "₹2,999",
      "price_num": 2999,
      "original_price": "₹4,95,000",
      "discount_pct": 99,
      "effective_price": null,
      "image_url": "",
      "category": "🏠 Home",
      "source": "amazon",
      "is_lowest_ever": false,
      "lowest_ever": null,
      "average_price": null,
      "highest_price": null,
      "vs_avg_str": null,
      "vs_avg_pct": null,
      "best_card_label": null,
      "best_card_discount": 0,
      "coupon": null,
      "coupon_num": 0,
      "emi_savings": null,
      "score": 20,
      "rating": 5.0,
      "affiliate_link": "https://www.amazon.in/dp/B0GTTT2N61?tag=techeasy0d1-21&linkCode=ll1&linkId=B0GTTT2N61&ref_=as_li_ss_tl",
      "posted_at": "2026-05-05T20:53:10.888962+00:00"
    },
    {
      "asin": "B0GTHZ3JX9",
      "title": "Buy Drumstone (Exclusive &amp; Limited 5 Year Warranty) Induction Cooktop 2000W Electric Stove Rapid Heating Cooking Plate, Shockproof Induction Chulha, Energy Efficient, Easy Clean Surface, Gas-Free Cooking Online at Low Prices in India - Amazon.in",
      "price": "₹2,999",
      "price_num": 2999,
      "original_price": "₹5,999",
      "discount_pct": 50,
      "effective_price": "₹2,910",
      "image_url": "https://m.media-amazon.com/images/I/61hS8AqWZQL._SL1024_.jpg",
      "category": "🔥 Hot Deal",
      "source": "amazon",
      "is_lowest_ever": false,
      "lowest_ever": null,
      "average_price": null,
      "highest_price": null,
      "vs_avg_str": null,
      "vs_avg_pct": null,
      "best_card_label": "₹89 off via Amazon Pay",
      "best_card_discount": 89,
      "coupon": null,
      "coupon_num": 0,
      "emi_savings": "₹97 EMI interest savings",
      "score": 20,
      "rating": 5.0,
      "affiliate_link": "https://www.amazon.in/dp/B0GTHZ3JX9?tag=techeasy0d1-21&linkCode=ll1&linkId=B0GTHZ3JX9&ref_=as_li_ss_tl",
      "posted_at": "2026-05-05T20:53:04.696934+00:00"
    },
    {
      "asin": "B0DCW1QV6K",
      "title": "Buy Bajaj GX1 Ninja Series 500W Mixer Grinder With 3 Jars (Stainless Steel Jars)",
      "price": "₹2,299",
      "price_num": 2299,
      "original_price": "₹11,999",
      "discount_pct": 80,
      "effective_price": "₹2,231",
      "image_url": "https://m.media-amazon.com/images/I/512xtc3OTEL._SL1200_.jpg",
      "category": "🍳 Kitchen",
      "source": "amazon",
      "is_lowest_ever": false,
      "lowest_ever": "₹1,715",
      "average_price": "₹2,264",
      "highest_price": "₹4,590",
      "vs_avg_str": "1% above avg (avg ₹2,264)",
      "vs_avg_pct": -1,
      "best_card_label": "₹68 off via Amazon Pay",
      "best_card_discount": 68,
      "coupon": null,
      "coupon_num": 0,
      "emi_savings": "₹74 EMI interest savings",
      "score": 20,
      "rating": 4.2,
      "affiliate_link": "https://www.amazon.in/dp/B0DCW1QV6K?tag=techeasy0d1-21&linkCode=ll1&linkId=B0DCW1QV6K&ref_=as_li_ss_tl",
      "posted_at": "2026-05-05T20:52:59.637715+00:00"
    },
    {
      "asin": "B0GHY76N2H",
      "title": "Buy F Gear Canyon 18L Premium Canvas Laptop Backpack",
      "price": "₹1,190",
      "price_num": 1190,
      "original_price": "₹2,580",
      "discount_pct": 53,
      "effective_price": null,
      "image_url": "https://m.media-amazon.com/images/I/71FZtCsUvzL._SL1500_.jpg",
      "category": "⚡ Electronics",
      "source": "amazon",
      "is_lowest_ever": false,
      "lowest_ever": null,
      "average_price": null,
      "highest_price": null,
      "vs_avg_str": null,
      "vs_avg_pct": null,
      "best_card_label": null,
      "best_card_discount": 0,
      "coupon": null,
      "coupon_num": 0,
      "emi_savings": null,
      "score": 20,
      "rating": 4.7,
      "affiliate_link": "https://www.amazon.in/dp/B0GHY76N2H?tag=techeasy0d1-21&linkCode=ll1&linkId=B0GHY76N2H&ref_=as_li_ss_tl",
      "posted_at": "2026-05-05T20:52:52.171718+00:00"
    },
    {
      "asin": "B0GTZ77GV7",
      "title": "Buy Drumstone 𝟏𝟓-𝐘𝐞𝐚𝐫 𝐋𝐨𝐧𝐠-𝐋𝐢𝐟𝐞 𝐖𝐚𝐫𝐫𝐚𝐧𝐭𝐲, electric induction stove 2000w, induction cooktops, induction stoves 2000w, portable induction chulha, electric stove for kitchen Online at Low Prices in India - Amazon.in",
      "price": "₹3,029",
      "price_num": 3029,
      "original_price": "₹6,290",
      "discount_pct": 51,
      "effective_price": "₹2,939",
      "image_url": "https://m.media-amazon.com/images/I/71cQTCmyQTL._SL1000_.jpg",
      "category": "🍳 Kitchen",
      "source": "amazon",
      "is_lowest_ever": false,
      "lowest_ever": null,
      "average_price": null,
      "highest_price": null,
      "vs_avg_str": null,
      "vs_avg_pct": null,
      "best_card_label": "₹90 off via Amazon Pay",
      "best_card_discount": 90,
      "coupon": null,
      "coupon_num": 0,
      "emi_savings": "₹98 EMI interest savings",
      "score": 20,
      "rating": 5.0,
      "affiliate_link": "https://www.amazon.in/dp/B0GTZ77GV7?tag=techeasy0d1-21&linkCode=ll1&linkId=B0GTZ77GV7&ref_=as_li_ss_tl",
      "posted_at": "2026-05-05T20:52:46.987593+00:00"
    },
    {
      "asin": "B09QQ4M8WV",
      "title": "Buy CooKNooK Pizza Mesh/Screen for Commercial Use of Hotels and Restaurant 7 Inches Diameter Alminium Pizza Mesh/Screen - Set of 6 Pieces Online at Low Prices in India - Amazon.in",
      "price": "₹650",
      "price_num": 650,
      "original_price": "₹1,500",
      "discount_pct": 56,
      "effective_price": null,
      "image_url": "https://m.media-amazon.com/images/I/51uTfcyD+sL._SL1024_.jpg",
      "category": "🔥 Hot Deal",
      "source": "amazon",
      "is_lowest_ever": false,
      "lowest_ever": null,
      "average_price": null,
      "highest_price": null,
      "vs_avg_str": null,
      "vs_avg_pct": null,
      "best_card_label": "₹19 off via Amazon Pay",
      "best_card_discount": 19,
      "coupon": null,
      "coupon_num": 0,
      "emi_savings": null,
      "score": 20,
      "rating": 4.2,
      "affiliate_link": "https://www.amazon.in/dp/B09QQ4M8WV?tag=techeasy0d1-21&linkCode=ll1&linkId=B09QQ4M8WV&ref_=as_li_ss_tl",
      "posted_at": "2026-05-05T20:52:39.959671+00:00"
    },
    {
      "asin": "B0F5BSNXR6",
      "title": "TheGiftKart Tough Armor Bumper Back Case Cover for iQOO Z10 5G / Vivo T4 5G",
      "price": "₹399",
      "price_num": 399,
      "original_price": "₹999",
      "discount_pct": 60,
      "effective_price": null,
      "image_url": "https://m.media-amazon.com/images/I/61XK2HDRTtL._SL1000_.jpg",
      "category": "🔥 Hot Deal",
      "source": "amazon",
      "is_lowest_ever": false,
      "lowest_ever": "₹320",
      "average_price": "₹375",
      "highest_price": "₹399",
      "vs_avg_str": "6% above avg (avg ₹375)",
      "vs_avg_pct": -6,
      "best_card_label": "₹11 off via Amazon Pay",
      "best_card_discount": 11,
      "coupon": null,
      "coupon_num": 0,
      "emi_savings": null,
      "score": 20,
      "rating": 4.5,
      "affiliate_link": "https://www.amazon.in/dp/B0F5BSNXR6?tag=techeasy0d1-21&linkCode=ll1&linkId=B0F5BSNXR6&ref_=as_li_ss_tl",
      "posted_at": "2026-05-05T20:52:34.093401+00:00"
    },
    {
      "asin": "B079GZ9JNB",
      "title": "SYGA 15 Holes Red Silicone Heart Shape Mold",
      "price": "₹169",
      "price_num": 169,
      "original_price": "₹458",
      "discount_pct": 63,
      "effective_price": null,
      "image_url": "https://m.media-amazon.com/images/I/718qpqTre4L._SL1500_.jpg",
      "category": "🔥 Hot Deal",
      "source": "amazon",
      "is_lowest_ever": false,
      "lowest_ever": null,
      "average_price": null,
      "highest_price": null,
      "vs_avg_str": null,
      "vs_avg_pct": null,
      "best_card_label": "₹5 off via Amazon Pay",
      "best_card_discount": 5,
      "coupon": null,
      "coupon_num": 0,
      "emi_savings": null,
      "score": 20,
      "rating": 4.2,
      "affiliate_link": "https://www.amazon.in/dp/B079GZ9JNB?tag=techeasy0d1-21&linkCode=ll1&linkId=B079GZ9JNB&ref_=as_li_ss_tl",
      "posted_at": "2026-05-05T20:52:25.931884+00:00"
    },
    {
      "asin": "B07FM7KHT4",
      "title": "17.3-Inch Laptop Shoulder Carrying Bag Case Sleeve for 16\" 16.5\" 17\" 17.3 inch Computer/Notebook/Ultrabook/Chromebook, Mermaid Scale (Colorful)",
      "price": "₹4,242",
      "price_num": 4242,
      "original_price": "₹14,240",
      "discount_pct": 70,
      "effective_price": "₹4,115",
      "image_url": "https://m.media-amazon.com/images/I/81Gzs7NVD8L._SL1500_.jpg",
      "category": "⚡ Electronics",
      "source": "amazon",
      "is_lowest_ever": false,
      "lowest_ever": null,
      "average_price": null,
      "highest_price": null,
      "vs_avg_str": null,
      "vs_avg_pct": null,
      "best_card_label": "₹127 off via Amazon Pay",
      "best_card_discount": 127,
      "coupon": null,
      "coupon_num": 0,
      "emi_savings": "₹137 EMI interest savings",
      "score": 20,
      "rating": 4.6,
      "affiliate_link": "https://www.amazon.in/dp/B07FM7KHT4?tag=techeasy0d1-21&linkCode=ll1&linkId=B07FM7KHT4&ref_=as_li_ss_tl",
      "posted_at": "2026-05-05T20:52:19.029379+00:00"
    },
    {
      "asin": "B0FH569G3V",
      "title": "Lifelong 4.2 Litre Digital Air Fryer",
      "price": "₹3,099",
      "price_num": 3099,
      "original_price": "₹12,499",
      "discount_pct": 75,
      "effective_price": "₹2,946",
      "image_url": "https://m.media-amazon.com/images/I/614LO9QNbKL._SL1500_.jpg",
      "category": "🔥 Hot Deal",
      "source": "amazon",
      "is_lowest_ever": false,
      "lowest_ever": "₹2,999",
      "average_price": "₹3,188",
      "highest_price": "₹4,000",
      "vs_avg_str": "2% below avg (avg ₹3,188)",
      "vs_avg_pct": 2,
      "best_card_label": "₹92 off via Amazon Pay",
      "best_card_discount": 92,
      "coupon": "2% off",
      "coupon_num": 61,
      "emi_savings": "₹100 EMI interest savings",
      "score": 22,
      "rating": 4.9,
      "affiliate_link": "https://www.amazon.in/dp/B0FH569G3V?tag=techeasy0d1-21&linkCode=ll1&linkId=B0FH569G3V&ref_=as_li_ss_tl",
      "posted_at": "2026-05-05T20:52:12.909797+00:00"
    },
    {
      "asin": "B0D266RR5T",
      "title": "PIXELARTZ Laptop Skin Abstract Graffiti Art Painting Floral HD Quality 15.6 Inches Multi Colour (7038, Full Body)",
      "price": "₹184",
      "price_num": 184,
      "original_price": "₹3,799",
      "discount_pct": 95,
      "effective_price": null,
      "image_url": "",
      "category": "⚡ Electronics",
      "source": "amazon",
      "is_lowest_ever": false,
      "lowest_ever": "₹149",
      "average_price": "₹236",
      "highest_price": "₹299",
      "vs_avg_str": "22% below avg (avg ₹236)",
      "vs_avg_pct": 22,
      "best_card_label": null,
      "best_card_discount": 0,
      "coupon": null,
      "coupon_num": 0,
      "emi_savings": null,
      "score": 42,
      "rating": 4.5,
      "affiliate_link": "https://www.amazon.in/dp/B0D266RR5T?tag=techeasy0d1-21&linkCode=ll1&linkId=B0D266RR5T&ref_=as_li_ss_tl",
      "posted_at": "2026-05-05T20:52:06.506587+00:00"
    },
    {
      "asin": "B0GTTZK495",
      "title": "Buy Drumstone (15 Years Replacement Warranty) Energy-Efficient 2000W Portable Induction Cooktop – Touch LED Display, Preset Menus, Quick Heating Electric Stove for Home, Office &amp; Travel Online at Low Prices in India - Amazon.in",
      "price": "₹2,999",
      "price_num": 2999,
      "original_price": "₹45,999",
      "discount_pct": 93,
      "effective_price": "₹2,910",
      "image_url": "",
      "category": "🏠 Home",
      "source": "amazon",
      "is_lowest_ever": true,
      "lowest_ever": "₹2,999",
      "average_price": "₹4,755",
      "highest_price": "₹8,599",
      "vs_avg_str": "36% below avg (avg ₹4,755)",
      "vs_avg_pct": 36,
      "best_card_label": "₹89 off via Amazon Pay",
      "best_card_discount": 89,
      "coupon": null,
      "coupon_num": 0,
      "emi_savings": "₹97 EMI interest savings",
      "score": 90,
      "rating": 5.0,
      "affiliate_link": "https://www.amazon.in/dp/B0GTTZK495?tag=techeasy0d1-21&linkCode=ll1&linkId=B0GTTZK495&ref_=as_li_ss_tl",
      "posted_at": "2026-05-05T20:52:00.269962+00:00"
    },
    {
      "asin": "B0GTTN8ZHX",
      "title": "Buy Lambent 𝟏𝟓-𝐘𝐞𝐚𝐫 𝐋𝐨𝐧𝐠-𝐋𝐢𝐟𝐞 𝐖𝐚𝐫𝐫𝐚𝐧𝐭𝐲 Professional Induction Cooktop, 2000 Watt Electric Stove, Infrared Heating Plate, Multi Purpose Cooking Modes, Easy Clean Surface, Home Use Online at Low Prices in India - Amazon.in",
      "price": "₹2,999",
      "price_num": 2999,
      "original_price": "₹5,999",
      "discount_pct": 50,
      "effective_price": "₹2,851",
      "image_url": "",
      "category": "🏠 Home",
      "source": "amazon",
      "is_lowest_ever": true,
      "lowest_ever": "₹2,999",
      "average_price": "₹4,660",
      "highest_price": "₹8,269",
      "vs_avg_str": "35% below avg (avg ₹4,660)",
      "vs_avg_pct": 35,
      "best_card_label": "₹89 off via Amazon Pay",
      "best_card_discount": 89,
      "coupon": "2% off",
      "coupon_num": 59,
      "emi_savings": "₹97 EMI interest savings",
      "score": 90,
      "rating": 5.0,
      "affiliate_link": "https://www.amazon.in/dp/B0GTTN8ZHX?tag=techeasy0d1-21&linkCode=ll1&linkId=B0GTTN8ZHX&ref_=as_li_ss_tl",
      "posted_at": "2026-05-05T20:51:53.613608+00:00"
    },
    {
      "asin": "B0GTVL8WZ7",
      "title": "Buy Drumstone (𝟏𝟓-𝐘𝐞𝐚𝐫𝐬 𝐰𝐚𝐫𝐫𝐚𝐧𝐭𝐲) 2000W Induction Cooktop with Touch Control, Digital Infrared Electric Stove, Fast Heating Glass Top, 8 Cooking Preset Menus Online at Low Prices in India - Amazon.in",
      "price": "₹3,029",
      "price_num": 3029,
      "original_price": "₹39,499",
      "discount_pct": 92,
      "effective_price": null,
      "image_url": "",
      "category": "🔥 Hot Deal",
      "source": "amazon",
      "is_lowest_ever": true,
      "lowest_ever": "₹3,169",
      "average_price": "₹4,842",
      "highest_price": "₹8,269",
      "vs_avg_str": "37% below avg (avg ₹4,842)",
      "vs_avg_pct": 37,
      "best_card_label": null,
      "best_card_discount": 0,
      "coupon": null,
      "coupon_num": 0,
      "emi_savings": null,
      "score": 90,
      "rating": 5.0,
      "affiliate_link": "https://www.amazon.in/dp/B0GTVL8WZ7?tag=techeasy0d1-21&linkCode=ll1&linkId=B0GTVL8WZ7&ref_=as_li_ss_tl",
      "posted_at": "2026-05-05T20:51:45.398889+00:00"
    },
    {
      "asin": "B0B7BFZ31S",
      "title": "Buy ACTIVA Volcano 3L Instant Water Heater Geyser",
      "price": "₹1,958",
      "price_num": 1958,
      "original_price": "₹4,990",
      "discount_pct": 60,
      "effective_price": "₹1,900",
      "image_url": "https://m.media-amazon.com/images/I/519s8YJ1JWL._SL1499_.jpg",
      "category": "🔥 Hot Deal",
      "source": "amazon",
      "is_lowest_ever": false,
      "lowest_ever": "₹1,699",
      "average_price": "₹1,884",
      "highest_price": "₹2,249",
      "vs_avg_str": "3% above avg (avg ₹1,884)",
      "vs_avg_pct": -3,
      "best_card_label": "₹58 off via Amazon Pay",
      "best_card_discount": 58,
      "coupon": null,
      "coupon_num": 0,
      "emi_savings": "₹63 EMI interest savings",
      "score": 20,
      "rating": 4.4,
      "affiliate_link": "https://www.amazon.in/dp/B0B7BFZ31S?tag=techeasy0d1-21&linkCode=ll1&linkId=B0B7BFZ31S&ref_=as_li_ss_tl",
      "posted_at": "2026-05-05T20:22:54.107529+00:00"
    },
    {
      "asin": "B0DQ615K72",
      "title": "Buy Drumstone 𝟏𝟓 𝐘𝐄𝐀𝐑𝐒 𝐖𝐀𝐑𝐑𝐀𝐍𝐓𝐘 Instant Geyser 1 Ltr, Portable Geyser for Kitchen &amp; Home, Compact Instant Water Heater, 3-Second Heating for Quick Hot Water 𝟏𝟎𝟎% 𝐂𝐨𝐩𝐩𝐞𝐫 Multicolor Online at Low Prices in India - Amazon.in",
      "price": "₹1,409",
      "price_num": 1409,
      "original_price": "₹3,999",
      "discount_pct": 64,
      "effective_price": null,
      "image_url": "",
      "category": "🏠 Home",
      "source": "amazon",
      "is_lowest_ever": false,
      "lowest_ever": null,
      "average_price": null,
      "highest_price": null,
      "vs_avg_str": null,
      "vs_avg_pct": null,
      "best_card_label": null,
      "best_card_discount": 0,
      "coupon": null,
      "coupon_num": 0,
      "emi_savings": null,
      "score": 20,
      "rating": 5.0,
      "affiliate_link": "https://www.amazon.in/dp/B0DQ615K72?tag=techeasy0d1-21&linkCode=ll1&linkId=B0DQ615K72&ref_=as_li_ss_tl",
      "posted_at": "2026-05-05T20:22:48.873637+00:00"
    },
    {
      "asin": "B0GPZC9KMQ",
      "title": "Pureplus 25 LPH Commercial RO +UV Protected Water Purifier System with Booster Pump, 3 Stage Pre-Filtration &amp; Heavy Duty Stainless Steel Frame",
      "price": "₹7,799",
      "price_num": 7799,
      "original_price": "₹24,999",
      "discount_pct": 68,
      "effective_price": "₹7,566",
      "image_url": "https://m.media-amazon.com/images/I/71-6pzpTpSL._SL1500_.jpg",
      "category": "🔥 Hot Deal",
      "source": "amazon",
      "is_lowest_ever": false,
      "lowest_ever": "₹7,499",
      "average_price": "₹7,774",
      "highest_price": "₹7,799",
      "vs_avg_str": "0% above avg (avg ₹7,774)",
      "vs_avg_pct": 0,
      "best_card_label": "₹233 off via Amazon Pay",
      "best_card_discount": 233,
      "coupon": null,
      "coupon_num": 0,
      "emi_savings": "₹252 EMI interest savings",
      "score": 20,
      "rating": 3.9,
      "affiliate_link": "https://www.amazon.in/dp/B0GPZC9KMQ?tag=techeasy0d1-21&linkCode=ll1&linkId=B0GPZC9KMQ&ref_=as_li_ss_tl",
      "posted_at": "2026-05-05T20:22:43.058593+00:00"
    },
    {
      "asin": "B0GPZGQ481",
      "title": "PurePlus 25 LPH Commercial RO Water Purifier with Double Purification, Booster Pump &amp; 3 Stage Pre-Filtration – Heavy Duty Stainless Steel System",
      "price": "₹7,799",
      "price_num": 7799,
      "original_price": "₹24,999",
      "discount_pct": 68,
      "effective_price": null,
      "image_url": "",
      "category": "🔥 Hot Deal",
      "source": "amazon",
      "is_lowest_ever": false,
      "lowest_ever": "₹7,499",
      "average_price": "₹7,774",
      "highest_price": "₹7,799",
      "vs_avg_str": "0% above avg (avg ₹7,774)",
      "vs_avg_pct": 0,
      "best_card_label": null,
      "best_card_discount": 0,
      "coupon": null,
      "coupon_num": 0,
      "emi_savings": null,
      "score": 20,
      "rating": 4.0,
      "affiliate_link": "https://www.amazon.in/dp/B0GPZGQ481?tag=techeasy0d1-21&linkCode=ll1&linkId=B0GPZGQ481&ref_=as_li_ss_tl",
      "posted_at": "2026-05-05T20:22:35.884053+00:00"
    },
    {
      "asin": "B0GPZZ1R5N",
      "title": "Pureplus 25 LPH Commercial RO Water Purifier System with Booster Pump, 3 Stage Pre-Filtration &amp; Heavy Duty Stainless Steel Frame",
      "price": "₹6,749",
      "price_num": 6749,
      "original_price": "₹24,999",
      "discount_pct": 73,
      "effective_price": "₹6,547",
      "image_url": "https://m.media-amazon.com/images/I/7148XTHq90L._SL1500_.jpg",
      "category": "🔥 Hot Deal",
      "source": "amazon",
      "is_lowest_ever": false,
      "lowest_ever": "₹6,449",
      "average_price": "₹6,725",
      "highest_price": "₹6,749",
      "vs_avg_str": "0% above avg (avg ₹6,725)",
      "vs_avg_pct": 0,
      "best_card_label": "₹202 off via Amazon Pay",
      "best_card_discount": 202,
      "coupon": null,
      "coupon_num": 0,
      "emi_savings": "₹218 EMI interest savings",
      "score": 20,
      "rating": 5.0,
      "affiliate_link": "https://www.amazon.in/dp/B0GPZZ1R5N?tag=techeasy0d1-21&linkCode=ll1&linkId=B0GPZZ1R5N&ref_=as_li_ss_tl",
      "posted_at": "2026-05-05T20:22:29.161336+00:00"
    },
    {
      "asin": "B0DF96JGRJ",
      "title": "AquaDart Mineral RO+UV+UF 12 Liter RO + UV + TDS ADJUSTER Water Purifier With Copper Charge Technology Black &amp; Copper Best For Home and Office (Made In India)",
      "price": "₹4,999",
      "price_num": 4999,
      "original_price": "₹24,999",
      "discount_pct": 80,
      "effective_price": "₹4,850",
      "image_url": "https://m.media-amazon.com/images/I/71wOsz5929L._SL1500_.jpg",
      "category": "🏠 Home",
      "source": "amazon",
      "is_lowest_ever": false,
      "lowest_ever": "₹4,699",
      "average_price": "₹4,914",
      "highest_price": "₹4,999",
      "vs_avg_str": "1% above avg (avg ₹4,914)",
      "vs_avg_pct": -1,
      "best_card_label": "₹149 off via Amazon Pay",
      "best_card_discount": 149,
      "coupon": null,
      "coupon_num": 0,
      "emi_savings": "₹162 EMI interest savings",
      "score": 20,
      "rating": 4.7,
      "affiliate_link": "https://www.amazon.in/dp/B0DF96JGRJ?tag=techeasy0d1-21&linkCode=ll1&linkId=B0DF96JGRJ&ref_=as_li_ss_tl",
      "posted_at": "2026-05-05T20:22:23.333226+00:00"
    },
    {
      "asin": "B0G1L11R15",
      "title": "iSpring Mineral RO+UV+UF 12 Liter RO + UV + TDS ADJUSTER Water Purifier With Copper Charge Technology Black &amp; Copper Best For Home and Office (Made In India)",
      "price": "₹4,999",
      "price_num": 4999,
      "original_price": "₹24,999",
      "discount_pct": 80,
      "effective_price": "₹4,850",
      "image_url": "https://m.media-amazon.com/images/I/61WMMfrBybL._SL1500_.jpg",
      "category": "🏠 Home",
      "source": "amazon",
      "is_lowest_ever": false,
      "lowest_ever": "₹4,748",
      "average_price": "₹4,994",
      "highest_price": "₹4,999",
      "vs_avg_str": "0% above avg (avg ₹4,994)",
      "vs_avg_pct": 0,
      "best_card_label": "₹149 off via Amazon Pay",
      "best_card_discount": 149,
      "coupon": null,
      "coupon_num": 0,
      "emi_savings": "₹162 EMI interest savings",
      "score": 20,
      "rating": 4.6,
      "affiliate_link": "https://www.amazon.in/dp/B0G1L11R15?tag=techeasy0d1-21&linkCode=ll1&linkId=B0G1L11R15&ref_=as_li_ss_tl",
      "posted_at": "2026-05-05T20:22:18.066682+00:00"
    },
    {
      "asin": "B0G1KX8CMW",
      "title": "iSpring Zinc Copper Alkaline Hydrogen RO Water Purifier",
      "price": "₹5,499",
      "price_num": 5499,
      "original_price": "₹24,999",
      "discount_pct": 78,
      "effective_price": "₹5,335",
      "image_url": "https://m.media-amazon.com/images/I/61HNcCwIrmL._SL1500_.jpg",
      "category": "🔥 Hot Deal",
      "source": "amazon",
      "is_lowest_ever": false,
      "lowest_ever": "₹5,199",
      "average_price": "₹5,486",
      "highest_price": "₹5,499",
      "vs_avg_str": "0% above avg (avg ₹5,486)",
      "vs_avg_pct": 0,
      "best_card_label": "₹164 off via Amazon Pay",
      "best_card_discount": 164,
      "coupon": null,
      "coupon_num": 0,
      "emi_savings": "₹178 EMI interest savings",
      "score": 20,
      "rating": 4.7,
      "affiliate_link": "https://www.amazon.in/dp/B0G1KX8CMW?tag=techeasy0d1-21&linkCode=ll1&linkId=B0G1KX8CMW&ref_=as_li_ss_tl",
      "posted_at": "2026-05-05T20:22:11.277417+00:00"
    },
    {
      "asin": "B0CVN74ZQM",
      "title": "Buy Lapras 𝟏𝟓 𝐘𝐞𝐚𝐫𝐬 𝐆𝐮𝐚𝐫𝐚𝐧𝐭𝐞𝐞 Instant electric tap water heater geyser with LED display, fast heating non leak design for kitchen bathroom and washbasin Online at Low Prices in India - Amazon.in",
      "price": "₹989",
      "price_num": 989,
      "original_price": "₹4,999",
      "discount_pct": 80,
      "effective_price": null,
      "image_url": "https://m.media-amazon.com/images/I/61q3mT69ZFL._SL1500_.jpg",
      "category": "🍳 Kitchen",
      "source": "amazon",
      "is_lowest_ever": false,
      "lowest_ever": null,
      "average_price": null,
      "highest_price": null,
      "vs_avg_str": null,
      "vs_avg_pct": null,
      "best_card_label": "₹29 off via Amazon Pay",
      "best_card_discount": 29,
      "coupon": "2% off",
      "coupon_num": 19,
      "emi_savings": null,
      "score": 20,
      "rating": 5.0,
      "affiliate_link": "https://www.amazon.in/dp/B0CVN74ZQM?tag=techeasy0d1-21&linkCode=ll1&linkId=B0CVN74ZQM&ref_=as_li_ss_tl",
      "posted_at": "2026-05-05T20:22:03.097109+00:00"
    },
    {
      "asin": "B0B93L7617",
      "title": "Aetrius Vacuum Cleaner for car use",
      "price": "₹1,199",
      "price_num": 1199,
      "original_price": "₹5,999",
      "discount_pct": 80,
      "effective_price": "₹805",
      "image_url": "",
      "category": "🔥 Hot Deal",
      "source": "amazon",
      "is_lowest_ever": false,
      "lowest_ever": "₹991",
      "average_price": "₹1,232",
      "highest_price": "₹1,549",
      "vs_avg_str": "2% below avg (avg ₹1,232)",
      "vs_avg_pct": 2,
      "best_card_label": "₹35 off via Amazon Pay",
      "best_card_discount": 35,
      "coupon": "30% off",
      "coupon_num": 359,
      "emi_savings": null,
      "score": 22,
      "rating": 4.4,
      "affiliate_link": "https://www.amazon.in/dp/B0B93L7617?tag=techeasy0d1-21&linkCode=ll1&linkId=B0B93L7617&ref_=as_li_ss_tl",
      "posted_at": "2026-05-05T20:21:55.640966+00:00"
    },
    {
      "asin": "B0GPZVGTQG",
      "title": "PurePlus 50 Liter Commercial RO Water Purifier Plant with TDS Adjuster Blue Stainless steel Full Automatic with TDS Adjuster",
      "price": "₹11,499",
      "price_num": 11499,
      "original_price": "₹29,999",
      "discount_pct": 61,
      "effective_price": "₹8,999",
      "image_url": "https://m.media-amazon.com/images/I/71H8SWoaEwL._SL1500_.jpg",
      "category": "🔥 Hot Deal",
      "source": "amazon",
      "is_lowest_ever": false,
      "lowest_ever": "₹10,999",
      "average_price": "₹11,465",
      "highest_price": "₹11,499",
      "vs_avg_str": "0% above avg (avg ₹11,465)",
      "vs_avg_pct": 0,
      "best_card_label": "₹2,500 off via select Credit",
      "best_card_discount": 2500,
      "coupon": null,
      "coupon_num": 0,
      "emi_savings": "₹372 EMI interest savings",
      "score": 22,
      "rating": 4.2,
      "affiliate_link": "https://www.amazon.in/dp/B0GPZVGTQG?tag=techeasy0d1-21&linkCode=ll1&linkId=B0GPZVGTQG&ref_=as_li_ss_tl",
      "posted_at": "2026-05-05T20:21:48.949469+00:00"
    },
    {
      "asin": "B0DW8Y8191",
      "title": "BISSELL CrossWave HF2 Wet &amp; Dry Hard Floor Cleaner",
      "price": "₹18,990",
      "price_num": 18990,
      "original_price": "₹69,950",
      "discount_pct": 72,
      "effective_price": "₹16,490",
      "image_url": "https://m.media-amazon.com/images/I/61aI2cwSwGL._SL1500_.jpg",
      "category": "🔥 Hot Deal",
      "source": "amazon",
      "is_lowest_ever": false,
      "lowest_ever": "₹8,990",
      "average_price": "₹12,875",
      "highest_price": "₹28,990",
      "vs_avg_str": "47% above avg (avg ₹12,875)",
      "vs_avg_pct": -47,
      "best_card_label": "₹2,500 off via select Credit",
      "best_card_discount": 2500,
      "coupon": null,
      "coupon_num": 0,
      "emi_savings": "₹1,060 EMI interest savings",
      "score": 22,
      "rating": 4.2,
      "affiliate_link": "https://www.amazon.in/dp/B0DW8Y8191?tag=techeasy0d1-21&linkCode=ll1&linkId=B0DW8Y8191&ref_=as_li_ss_tl",
      "posted_at": "2026-05-05T20:21:42.025020+00:00"
    },
    {
      "asin": "B0D6R19L4F",
      "title": "Buy Colorbot Helix BLDC Ceiling Fans 1200mm",
      "price": "₹2,999",
      "price_num": 2999,
      "original_price": "₹7,089",
      "discount_pct": 57,
      "effective_price": null,
      "image_url": "",
      "category": "🔥 Hot Deal",
      "source": "amazon",
      "is_lowest_ever": false,
      "lowest_ever": "₹2,659",
      "average_price": "₹3,133",
      "highest_price": "₹3,899",
      "vs_avg_str": "4% below avg (avg ₹3,133)",
      "vs_avg_pct": 4,
      "best_card_label": null,
      "best_card_discount": 0,
      "coupon": null,
      "coupon_num": 0,
      "emi_savings": null,
      "score": 24,
      "rating": 4.4,
      "affiliate_link": "https://www.amazon.in/dp/B0D6R19L4F?tag=techeasy0d1-21&linkCode=ll1&linkId=B0D6R19L4F&ref_=as_li_ss_tl",
      "posted_at": "2026-05-05T20:21:36.147480+00:00"
    },
    {
      "asin": "B082D8Q1C7",
      "title": "ODISTAR Desktop Vacuum Cleaner,Mini Table dust Sweeper Energy Saving,High Endurance up to 400 mins,Cordless&amp;360º Rotatable Design for Cleaning Hairs,Crumbs,Computer Keyboard (Black Charging)",
      "price": "₹2,977",
      "price_num": 2977,
      "original_price": "₹13,999",
      "discount_pct": 78,
      "effective_price": "₹2,888",
      "image_url": "https://m.media-amazon.com/images/I/41xSXR-Jf3L._SL1000_.jpg",
      "category": "🔥 Hot Deal",
      "source": "amazon",
      "is_lowest_ever": false,
      "lowest_ever": "₹1,599",
      "average_price": "₹3,306",
      "highest_price": "₹5,005",
      "vs_avg_str": "9% below avg (avg ₹3,306)",
      "vs_avg_pct": 9,
      "best_card_label": "₹89 off via Amazon Pay",
      "best_card_discount": 89,
      "coupon": null,
      "coupon_num": 0,
      "emi_savings": "₹96 EMI interest savings",
      "score": 29,
      "rating": 4.2,
      "affiliate_link": "https://www.amazon.in/dp/B082D8Q1C7?tag=techeasy0d1-21&linkCode=ll1&linkId=B082D8Q1C7&ref_=as_li_ss_tl",
      "posted_at": "2026-05-05T20:21:31.095813+00:00"
    },
    {
      "asin": "B0GHP8PV5T",
      "title": "pTron Studio Ultima w/ 60Hrs Playtime, Dual Device Pairing, 40mm Drivers, Custom EQ, Mobile App, Wireless Over Ear Headphones w/HD Mic &amp; TruTalk AI-ENC Calls, BTv5.4 &amp; Type-C Charging (Jet Black)",
      "price": "₹1,699",
      "price_num": 1699,
      "original_price": "₹5,999",
      "discount_pct": 71,
      "effective_price": "₹1,649",
      "image_url": "https://m.media-amazon.com/images/I/61MadwUi7SL._SL1200_.jpg",
      "category": "⚡ Electronics",
      "source": "amazon",
      "is_lowest_ever": true,
      "lowest_ever": "₹1,699",
      "average_price": "₹1,712",
      "highest_price": "₹1,999",
      "vs_avg_str": "0% above avg (avg ₹1,712)",
      "vs_avg_pct": 0,
      "best_card_label": "₹50 off via Amazon Pay",
      "best_card_discount": 50,
      "coupon": null,
      "coupon_num": 0,
      "emi_savings": "₹55 EMI interest savings",
      "score": 60,
      "rating": 4.9,
      "affiliate_link": "https://www.amazon.in/dp/B0GHP8PV5T?tag=techeasy0d1-21&linkCode=ll1&linkId=B0GHP8PV5T&ref_=as_li_ss_tl",
      "posted_at": "2026-05-05T20:21:23.213993+00:00"
    },
    {
      "asin": "B0GNV4G1V9",
      "title": "Buy (15 Year Warranty) Instant Electric Water Heater with Fast Heating Copper Coil Durable ABS Body Auto Shut Off Safety for Bathroom and Kitchen Use Portable Compact Design Home- Green Online at Low Prices in India - Amazon.in",
      "price": "₹1,499",
      "price_num": 1499,
      "original_price": "₹4,999",
      "discount_pct": 70,
      "effective_price": null,
      "image_url": "",
      "category": "🏠 Home",
      "source": "amazon",
      "is_lowest_ever": true,
      "lowest_ever": "₹1,499",
      "average_price": "₹1,499",
      "highest_price": "₹1,499",
      "vs_avg_str": "0% above avg (avg ₹1,499)",
      "vs_avg_pct": 0,
      "best_card_label": null,
      "best_card_discount": 0,
      "coupon": null,
      "coupon_num": 0,
      "emi_savings": null,
      "score": 60,
      "rating": 4.3,
      "affiliate_link": "https://www.amazon.in/dp/B0GNV4G1V9?tag=techeasy0d1-21&linkCode=ll1&linkId=B0GNV4G1V9&ref_=as_li_ss_tl",
      "posted_at": "2026-05-05T20:21:17.059632+00:00"
    },
    {
      "asin": "B0GQJJSLY1",
      "title": "Blackwik Military-Grade Gorilla Tempered Glass for Google Pixel 10 (Black)",
      "price": "₹299",
      "price_num": 299,
      "original_price": "₹999",
      "discount_pct": 70,
      "effective_price": null,
      "image_url": "https://m.media-amazon.com/images/I/61ro6t41xML._SL1500_.jpg",
      "category": "🔥 Hot Deal",
      "source": "amazon",
      "is_lowest_ever": true,
      "lowest_ever": "₹299",
      "average_price": "₹299",
      "highest_price": "₹299",
      "vs_avg_str": "0% above avg (avg ₹299)",
      "vs_avg_pct": 0,
      "best_card_label": "₹8 off via Amazon Pay",
      "best_card_discount": 8,
      "coupon": "2% off",
      "coupon_num": 5,
      "emi_savings": null,
      "score": 60,
      "rating": 4.9,
      "affiliate_link": "https://www.amazon.in/dp/B0GQJJSLY1?tag=techeasy0d1-21&linkCode=ll1&linkId=B0GQJJSLY1&ref_=as_li_ss_tl",
      "posted_at": "2026-05-05T20:21:10.949983+00:00"
    },
    {
      "asin": "B0GPZ3VMTZ",
      "title": "Pureplus Zinc Copper RO Water Purifier with UV, UF and TDS Controller Fully Automatic Function 12Liter Large Storage Tank, Suitable for all type of water supply and Best For (Home and Office)",
      "price": "₹5,499",
      "price_num": 5499,
      "original_price": "₹23,999",
      "discount_pct": 77,
      "effective_price": "₹5,335",
      "image_url": "https://m.media-amazon.com/images/I/61OortYORKL._SL1500_.jpg",
      "category": "🏠 Home",
      "source": "amazon",
      "is_lowest_ever": true,
      "lowest_ever": "₹5,499",
      "average_price": "₹5,499",
      "highest_price": "₹5,499",
      "vs_avg_str": "0% above avg (avg ₹5,499)",
      "vs_avg_pct": 0,
      "best_card_label": "₹164 off via Amazon Pay",
      "best_card_discount": 164,
      "coupon": null,
      "coupon_num": 0,
      "emi_savings": "₹178 EMI interest savings",
      "score": 60,
      "rating": 4.6,
      "affiliate_link": "https://www.amazon.in/dp/B0GPZ3VMTZ?tag=techeasy0d1-21&linkCode=ll1&linkId=B0GPZ3VMTZ&ref_=as_li_ss_tl",
      "posted_at": "2026-05-05T20:21:03.003110+00:00"
    },
    {
      "asin": "B0GVB7C5B9",
      "title": "iSpring 50 LPH Commercial RO Water Purifier Plant with TDS Adjuster 50 Litre Blue Stainless steel Full Automatic with TDS Adjuster",
      "price": "₹10,999",
      "price_num": 10999,
      "original_price": "₹34,499",
      "discount_pct": 68,
      "effective_price": "₹8,499",
      "image_url": "https://m.media-amazon.com/images/I/71byj1ayuuL._SL1500_.jpg",
      "category": "🔥 Hot Deal",
      "source": "amazon",
      "is_lowest_ever": true,
      "lowest_ever": "₹10,999",
      "average_price": "₹10,999",
      "highest_price": "₹10,999",
      "vs_avg_str": "0% above avg (avg ₹10,999)",
      "vs_avg_pct": 0,
      "best_card_label": "₹2,500 off via select Credit",
      "best_card_discount": 2500,
      "coupon": null,
      "coupon_num": 0,
      "emi_savings": "₹356 EMI interest savings",
      "score": 62,
      "rating": 4.6,
      "affiliate_link": "https://www.amazon.in/dp/B0GVB7C5B9?tag=techeasy0d1-21&linkCode=ll1&linkId=B0GVB7C5B9&ref_=as_li_ss_tl",
      "posted_at": "2026-05-05T20:20:55.134960+00:00"
    },
    {
      "asin": "B0GSFN886B",
      "title": "Godrej 185 L 4 Star Rating",
      "price": "₹15,690",
      "price_num": 15690,
      "original_price": "₹52,190",
      "discount_pct": 69,
      "effective_price": null,
      "image_url": "",
      "category": "🔥 Hot Deal",
      "source": "amazon",
      "is_lowest_ever": true,
      "lowest_ever": "₹15,690",
      "average_price": "₹16,258",
      "highest_price": "₹17,395",
      "vs_avg_str": "3% below avg (avg ₹16,258)",
      "vs_avg_pct": 3,
      "best_card_label": null,
      "best_card_discount": 0,
      "coupon": null,
      "coupon_num": 0,
      "emi_savings": null,
      "score": 63,
      "rating": null,
      "affiliate_link": "https://www.amazon.in/dp/B0GSFN886B?tag=techeasy0d1-21&linkCode=ll1&linkId=B0GSFN886B&ref_=as_li_ss_tl",
      "posted_at": "2026-05-05T20:20:48.540619+00:00"
    },
    {
      "asin": "B097LR4K45",
      "title": "IVELECT Universal 5V Car Mini Fridge Warmer and Cooler Dual Auto USB Refrigerator Freezer Office Black",
      "price": "₹4,533",
      "price_num": 4533,
      "original_price": "₹9,066",
      "discount_pct": 50,
      "effective_price": "₹4,398",
      "image_url": "https://m.media-amazon.com/images/I/41kYxwogQeL._SL1024_.jpg",
      "category": "⚡ Electronics",
      "source": "amazon",
      "is_lowest_ever": false,
      "lowest_ever": "₹2,812",
      "average_price": "₹4,179",
      "highest_price": "₹6,382",
      "vs_avg_str": "8% above avg (avg ₹4,179)",
      "vs_avg_pct": -8,
      "best_card_label": "₹135 off via Amazon Pay",
      "best_card_discount": 135,
      "coupon": null,
      "coupon_num": 0,
      "emi_savings": "₹147 EMI interest savings",
      "score": 20,
      "rating": 5.0,
      "affiliate_link": "https://www.amazon.in/dp/B097LR4K45?tag=techeasy0d1-21&linkCode=ll1&linkId=B097LR4K45&ref_=as_li_ss_tl",
      "posted_at": "2026-05-05T19:51:21.290098+00:00"
    },
    {
      "asin": "B081Q8WKCB",
      "title": "Ant Esports KM540 Gaming Keyboard and Mouse Combo",
      "price": "₹999",
      "price_num": 999,
      "original_price": "₹72,900",
      "discount_pct": 98,
      "effective_price": null,
      "image_url": "https://m.media-amazon.com/images/I/718wvGJlouL._SL1500_.jpg",
      "category": "🎮 Video Games",
      "source": "amazon",
      "is_lowest_ever": false,
      "lowest_ever": "₹949",
      "average_price": "₹1,594",
      "highest_price": "₹2,650",
      "vs_avg_str": "37% below avg (avg ₹1,594)",
      "vs_avg_pct": 37,
      "best_card_label": "₹29 off via Amazon Pay",
      "best_card_discount": 29,
      "coupon": null,
      "coupon_num": 0,
      "emi_savings": null,
      "score": 50,
      "rating": 4.1,
      "affiliate_link": "https://www.amazon.in/dp/B081Q8WKCB?tag=techeasy0d1-21&linkCode=ll1&linkId=B081Q8WKCB&ref_=as_li_ss_tl",
      "posted_at": "2026-05-05T19:51:15.831998+00:00"
    },
    {
      "asin": "B0GR1JFTPR",
      "title": "Apple 2026 MacBook Air 13″ Laptop with M5 chip",
      "price": "₹111,490",
      "price_num": 111490,
      "original_price": "₹2,34,900",
      "discount_pct": 52,
      "effective_price": "₹104,490",
      "image_url": "https://m.media-amazon.com/images/I/71upqrupfYL._SL1500_.jpg",
      "category": "⚡ Electronics",
      "source": "desidime",
      "is_lowest_ever": true,
      "lowest_ever": "₹111,490",
      "average_price": "₹117,779",
      "highest_price": "₹119,900",
      "vs_avg_str": "5% below avg (avg ₹117,779)",
      "vs_avg_pct": 5,
      "best_card_label": "₹7,000 off via select Credit",
      "best_card_discount": 7000,
      "coupon": null,
      "coupon_num": 0,
      "emi_savings": "₹5,174 EMI interest savings",
      "score": 72,
      "rating": 5.0,
      "affiliate_link": "https://www.amazon.in/dp/B0GR1JFTPR?tag=techeasy0d1-21&linkCode=ll1&linkId=B0GR1JFTPR&ref_=as_li_ss_tl",
      "posted_at": "2026-05-05T19:51:10.002454+00:00"
    },
    {
      "asin": "B00ENMK1DW",
      "title": "PHILIPS SHP9500 Over-Ear Headphones, HiFi Stereo, 50mm Neodymium Drivers, 101 dB, Breathable Ear Cushion, Steel Headband, Detachable 1.5m Cable, Gold-Plated 3.5mm Jack, Double Layered Cushion (Black)",
      "price": "₹6,499",
      "price_num": 6499,
      "original_price": "₹20,990",
      "discount_pct": 69,
      "effective_price": "₹3,999",
      "image_url": "https://m.media-amazon.com/images/I/71h7X9MueZL._SL1500_.jpg",
      "category": "⚡ Electronics",
      "source": "amazon",
      "is_lowest_ever": true,
      "lowest_ever": "₹6,499",
      "average_price": "₹12,617",
      "highest_price": "₹36,789",
      "vs_avg_str": "48% below avg (avg ₹12,617)",
      "vs_avg_pct": 48,
      "best_card_label": "₹2,500 off via select Credit",
      "best_card_discount": 2500,
      "coupon": null,
      "coupon_num": 0,
      "emi_savings": "₹210 EMI interest savings",
      "score": 92,
      "affiliate_link": "https://www.amazon.in/dp/B00ENMK1DW?tag=techeasy0d1-21&linkCode=ll1&linkId=B00ENMK1DW&ref_=as_li_ss_tl",
      "posted_at": "2026-05-04T19:48:17.056064+00:00"
    },
    {
      "asin": "B09NLK5YW9",
      "title": "Vilsaw Smart Watch, Fitness Smartwatch with Heart Rate Monitor &amp; Sleep Monitor Health and Fitness Tracker with SpO2 Compatible with iPhone and Android Phones",
      "price": "₹3,245",
      "price_num": 3245,
      "original_price": "₹6,422",
      "discount_pct": 49,
      "effective_price": "₹1,947",
      "image_url": "https://m.media-amazon.com/images/I/617Gs0jZJuL._SL1500_.jpg",
      "category": "⚡ Electronics",
      "source": "amazon",
      "is_lowest_ever": true,
      "lowest_ever": "₹3,246",
      "average_price": "₹5,175",
      "highest_price": "₹9,820",
      "vs_avg_str": "37% below avg (avg ₹5,175)",
      "vs_avg_pct": 37,
      "best_card_label": "₹1,298 off via select Credit",
      "best_card_discount": 1298,
      "coupon": null,
      "coupon_num": 0,
      "emi_savings": "₹84 EMI interest savings",
      "score": 91,
      "affiliate_link": "https://www.amazon.in/dp/B09NLK5YW9?tag=techeasy0d1-21&linkCode=ll1&linkId=B09NLK5YW9&ref_=as_li_ss_tl",
      "posted_at": "2026-05-05T18:56:43.132995+00:00"
    },
    {
      "asin": "B0GTV9RQXT",
      "title": "Buy Drumstone (𝐄𝐱𝐥𝐮𝐬𝐢𝐯𝐞 𝟐𝟎 𝐘𝐞𝐚𝐫𝐬 𝐰𝐚𝐫𝐫𝐚𝐧𝐭𝐲) Portable 2000W Induction Cooktop – Smart Menus, Timer, Fast Heating, Energy Efficient Glass Top Online at Low Prices in India - Amazon.in",
      "price": "₹2,999",
      "price_num": 2999,
      "original_price": "₹6,99,900",
      "discount_pct": 99,
      "effective_price": "₹1,800",
      "image_url": "https://m.media-amazon.com/images/I/519CQJeqGPL._SL1024_.jpg",
      "category": "🔥 Hot Deal",
      "source": "amazon",
      "is_lowest_ever": true,
      "lowest_ever": "₹2,999",
      "average_price": "₹4,469",
      "highest_price": "₹8,599",
      "vs_avg_str": "32% below avg (avg ₹4,469)",
      "vs_avg_pct": 32,
      "best_card_label": "₹1,199 off via select Credit",
      "best_card_discount": 1199,
      "coupon": null,
      "coupon_num": 0,
      "emi_savings": "₹97 EMI interest savings",
      "score": 91,
      "affiliate_link": "https://www.amazon.in/dp/B0GTV9RQXT?tag=techeasy0d1-21&linkCode=ll1&linkId=B0GTV9RQXT&ref_=as_li_ss_tl",
      "posted_at": "2026-05-05T18:11:01.690686+00:00"
    },
    {
      "asin": "B08HC8S93P",
      "title": "Balzano Digital Air Fryer (Extra Large 5.5Liter), uses up to 95% Less Fat, 1700W, with Rapid Heat Circulation Technology (Black)",
      "price": "₹3,999",
      "price_num": 3999,
      "original_price": "₹11,990",
      "discount_pct": 66,
      "effective_price": "₹2,400",
      "image_url": "https://m.media-amazon.com/images/I/61gA344QuKL._SL1500_.jpg",
      "category": "🔥 Hot Deal",
      "source": "amazon",
      "is_lowest_ever": true,
      "lowest_ever": "₹3,999",
      "average_price": "₹7,011",
      "highest_price": "₹9,490",
      "vs_avg_str": "42% below avg (avg ₹7,011)",
      "vs_avg_pct": 42,
      "best_card_label": "₹1,599 off via select Credit",
      "best_card_discount": 1599,
      "coupon": null,
      "coupon_num": 0,
      "emi_savings": "₹129 EMI interest savings",
      "score": 91,
      "affiliate_link": "https://www.amazon.in/dp/B08HC8S93P?tag=techeasy0d1-21&linkCode=ll1&linkId=B08HC8S93P&ref_=as_li_ss_tl",
      "posted_at": "2026-05-05T03:25:04.672062+00:00"
    },
    {
      "asin": "B0FN7N2FZT",
      "title": "TAG Gamerz Titan RGB White Over-Ear Gaming Wired Headphone",
      "price": "₹915",
      "price_num": 915,
      "original_price": "₹3,999",
      "discount_pct": 77,
      "effective_price": "₹549",
      "image_url": "https://m.media-amazon.com/images/I/61AY+QsRNSL._SL1500_.jpg",
      "category": "⚡ Electronics",
      "source": "desidime",
      "is_lowest_ever": true,
      "lowest_ever": "₹915",
      "average_price": "₹1,569",
      "highest_price": "₹2,199",
      "vs_avg_str": "41% below avg (avg ₹1,569)",
      "vs_avg_pct": 41,
      "best_card_label": "₹366 off via select Credit",
      "best_card_discount": 366,
      "coupon": null,
      "coupon_num": 0,
      "emi_savings": null,
      "score": 90,
      "affiliate_link": "https://www.amazon.in/dp/B0FN7N2FZT?tag=techeasy0d1-21&linkCode=ll1&linkId=B0FN7N2FZT&ref_=as_li_ss_tl",
      "posted_at": "2026-05-05T19:21:59.689746+00:00"
    },
    {
      "asin": "B0CNXBTJNF",
      "title": "beatXP Jiggle Sonic Electric Toothbrush for Kids with 2 Brush Heads &amp; 3 Cleaning Modes",
      "price": "₹299",
      "price_num": 299,
      "original_price": "₹1,499",
      "discount_pct": 80,
      "effective_price": null,
      "image_url": "https://m.media-amazon.com/images/I/61f5lIiL1UL._SL1500_.jpg",
      "category": "🔥 Hot Deal",
      "source": "amazon",
      "is_lowest_ever": true,
      "lowest_ever": "₹299",
      "average_price": "₹440",
      "highest_price": "₹953",
      "vs_avg_str": "32% below avg (avg ₹440)",
      "vs_avg_pct": 32,
      "best_card_label": null,
      "best_card_discount": 0,
      "coupon": null,
      "coupon_num": 0,
      "emi_savings": null,
      "score": 90,
      "affiliate_link": "https://www.amazon.in/dp/B0CNXBTJNF?tag=techeasy0d1-21&linkCode=ll1&linkId=B0CNXBTJNF&ref_=as_li_ss_tl",
      "posted_at": "2026-05-05T18:52:37.723612+00:00"
    },
    {
      "asin": "B0CNX9RYP3",
      "title": "beatXP Spark Sonic Electric Toothbrush for Adults with 2 Brush Heads &amp; Smart Cleaning Modes",
      "price": "₹499",
      "price_num": 499,
      "original_price": "₹3,499",
      "discount_pct": 85,
      "effective_price": null,
      "image_url": "https://m.media-amazon.com/images/I/61eeHYFQ2LL._SL1500_.jpg",
      "category": "🔥 Hot Deal",
      "source": "amazon",
      "is_lowest_ever": true,
      "lowest_ever": "₹499",
      "average_price": "₹1,090",
      "highest_price": "₹3,499",
      "vs_avg_str": "54% below avg (avg ₹1,090)",
      "vs_avg_pct": 54,
      "best_card_label": null,
      "best_card_discount": 0,
      "coupon": null,
      "coupon_num": 0,
      "emi_savings": null,
      "score": 90,
      "affiliate_link": "https://www.amazon.in/dp/B0CNX9RYP3?tag=techeasy0d1-21&linkCode=ll1&linkId=B0CNX9RYP3&ref_=as_li_ss_tl",
      "posted_at": "2026-05-05T18:52:31.309372+00:00"
    },
    {
      "asin": "B0BNP12RYR",
      "title": "Maplekart Travel Kettle Electric Small Foldable Portable Kettle,Silicone Collapsible Heating Water Boiler Tea Pot for Camping,Easy for Storage with Separable Power Cord (Multicolor)",
      "price": "₹488",
      "price_num": 488,
      "original_price": "₹1,999",
      "discount_pct": 75,
      "effective_price": "₹279",
      "image_url": "https://m.media-amazon.com/images/I/51VcCT+nidL._SL1500_.jpg",
      "category": "🍳 Kitchen",
      "source": "amazon",
      "is_lowest_ever": true,
      "lowest_ever": "₹488",
      "average_price": "₹791",
      "highest_price": "₹999",
      "vs_avg_str": "38% below avg (avg ₹791)",
      "vs_avg_pct": 38,
      "best_card_label": "₹195 off via select Credit",
      "best_card_discount": 195,
      "coupon": "3% off",
      "coupon_num": 14,
      "emi_savings": null,
      "score": 90,
      "affiliate_link": "https://www.amazon.in/dp/B0BNP12RYR?tag=techeasy0d1-21&linkCode=ll1&linkId=B0BNP12RYR&ref_=as_li_ss_tl",
      "posted_at": "2026-05-05T18:11:07.708094+00:00"
    },
    {
      "asin": "B0FM79988P",
      "title": "Kids Camera Digital Camera for Age 3-8,1080P HD Video Selfie Toddler Camera with Soft Cover, Christmas Birthday Gifts for Kids - 32GB SD Card - Pink",
      "price": "₹1,288",
      "price_num": 1288,
      "original_price": "₹2,599",
      "discount_pct": 50,
      "effective_price": "₹773",
      "image_url": "https://m.media-amazon.com/images/I/71EZ8MhvKwL._SL1500_.jpg",
      "category": "⚡ Electronics",
      "source": "amazon",
      "is_lowest_ever": true,
      "lowest_ever": "₹1,288",
      "average_price": "₹3,115",
      "highest_price": "₹5,628",
      "vs_avg_str": "58% below avg (avg ₹3,115)",
      "vs_avg_pct": 58,
      "best_card_label": "₹515 off via select Credit",
      "best_card_discount": 515,
      "coupon": null,
      "coupon_num": 0,
      "emi_savings": null,
      "score": 90,
      "affiliate_link": "https://www.amazon.in/dp/B0FM79988P?tag=techeasy0d1-21&linkCode=ll1&linkId=B0FM79988P&ref_=as_li_ss_tl",
      "posted_at": "2026-05-05T16:52:18.737172+00:00"
    }
  ]
}