{"slot": "2026-06-12_noon", "slot_name": "🌟 Noon Edition", "date": "12 Jun 2026", "items": [{"label": "📱 Best Phone", "title": "Samsung Galaxy S24 5G AI Smartphone", "price": "₹51,999", "original": "₹74,999", "discount": 30, "image": "", "link": "https://www.amazon.in/dp/B0CS62KYQY?tag=techeasy0d1-21&linkCode=ll1&linkId=B0CS62KYQY&ref_=as_li_ss_tl", "store": "Amazon", "is_lowest_ever": false, "vs_avg_pct": -2}, {"label": "💻 Best Laptop", "title": "ASUS Vivobook 16, Smartchoice, Intel Core Ultra 5 Series 2, 16GB RAM, 512GB SSD,", "price": "₹67,990", "original": "₹99,990", "discount": 32, "image": "https://m.media-amazon.com/images/I/714zVJcMt5L._SL1500_.jpg", "link": "https://www.amazon.in/dp/B0DT74FF9P?tag=techeasy0d1-21&linkCode=ll1&linkId=B0DT74FF9P&ref_=as_li_ss_tl", "store": "Amazon", "is_lowest_ever": false, "vs_avg_pct": 2}]}